[{"id":577597,"il_id":33,"ilce_id":1892,"mahalle_id":182459,"ad":"1","tip":"1 (Sokak)"},{"id":550444,"il_id":33,"ilce_id":1892,"mahalle_id":182459,"ad":"1 (Camii)","tip":"1 (Camii) (Sokak)"},{"id":387989,"il_id":33,"ilce_id":1892,"mahalle_id":182459,"ad":"1 (Orta)-","tip":"1 (Orta)- (Sokak)"},{"id":364695,"il_id":33,"ilce_id":1892,"mahalle_id":182459,"ad":"10","tip":"10 (Sokak)"},{"id":609049,"il_id":33,"ilce_id":1892,"mahalle_id":182459,"ad":"101","tip":"101 (Sokak)"},{"id":580926,"il_id":33,"ilce_id":1892,"mahalle_id":182459,"ad":"102","tip":"102 (Sokak)"},{"id":601632,"il_id":33,"ilce_id":1892,"mahalle_id":182459,"ad":"103","tip":"103 (Sokak)"},{"id":90347,"il_id":33,"ilce_id":1892,"mahalle_id":182459,"ad":"104","tip":"104 (Sokak)"},{"id":582276,"il_id":33,"ilce_id":1892,"mahalle_id":182459,"ad":"109","tip":"109 (Sokak)"},{"id":265351,"il_id":33,"ilce_id":1892,"mahalle_id":182459,"ad":"11","tip":"11 (Sokak)"},{"id":114365,"il_id":33,"ilce_id":1892,"mahalle_id":182459,"ad":"110","tip":"110 (Sokak)"},{"id":114372,"il_id":33,"ilce_id":1892,"mahalle_id":182459,"ad":"113-","tip":"113- (Sokak)"},{"id":581812,"il_id":33,"ilce_id":1892,"mahalle_id":182459,"ad":"114","tip":"114 (Sokak)"},{"id":560345,"il_id":33,"ilce_id":1892,"mahalle_id":182459,"ad":"117","tip":"117 (Sokak)"},{"id":551484,"il_id":33,"ilce_id":1892,"mahalle_id":182459,"ad":"119","tip":"119 (Sokak)"},{"id":114714,"il_id":33,"ilce_id":1892,"mahalle_id":182459,"ad":"120","tip":"120 (Sokak)"},{"id":554104,"il_id":33,"ilce_id":1892,"mahalle_id":182459,"ad":"121","tip":"121 (Sokak)"},{"id":550694,"il_id":33,"ilce_id":1892,"mahalle_id":182459,"ad":"122","tip":"122 (Sokak)"},{"id":750396,"il_id":33,"ilce_id":1892,"mahalle_id":182459,"ad":"123","tip":"123 (Sokak)"},{"id":550695,"il_id":33,"ilce_id":1892,"mahalle_id":182459,"ad":"123 (Orta)-","tip":"123 (Orta)- (Sokak)"},{"id":550909,"il_id":33,"ilce_id":1892,"mahalle_id":182459,"ad":"124","tip":"124 (Sokak)"},{"id":551837,"il_id":33,"ilce_id":1892,"mahalle_id":182459,"ad":"125","tip":"125 (Sokak)"},{"id":555977,"il_id":33,"ilce_id":1892,"mahalle_id":182459,"ad":"126","tip":"126 (Sokak)"},{"id":550911,"il_id":33,"ilce_id":1892,"mahalle_id":182459,"ad":"128","tip":"128 (Sokak)"},{"id":713396,"il_id":33,"ilce_id":1892,"mahalle_id":182459,"ad":"129","tip":"129 (Sokak)"},{"id":606360,"il_id":33,"ilce_id":1892,"mahalle_id":182459,"ad":"129 (Bozali)-","tip":"129 (Bozali)- (Sokak)"},{"id":550910,"il_id":33,"ilce_id":1892,"mahalle_id":182459,"ad":"129 (Orta)-","tip":"129 (Orta)- (Sokak)"},{"id":369668,"il_id":33,"ilce_id":1892,"mahalle_id":182459,"ad":"13","tip":"13 (Sokak)"},{"id":593339,"il_id":33,"ilce_id":1892,"mahalle_id":182459,"ad":"131","tip":"131 (Sokak)"},{"id":593340,"il_id":33,"ilce_id":1892,"mahalle_id":182459,"ad":"132","tip":"132 (Sokak)"},{"id":552343,"il_id":33,"ilce_id":1892,"mahalle_id":182459,"ad":"132 (Orta)-","tip":"132 (Orta)- (Sokak)"},{"id":591985,"il_id":33,"ilce_id":1892,"mahalle_id":182459,"ad":"133","tip":"133 (Sokak)"},{"id":592404,"il_id":33,"ilce_id":1892,"mahalle_id":182459,"ad":"134","tip":"134 (Sokak)"},{"id":594175,"il_id":33,"ilce_id":1892,"mahalle_id":182459,"ad":"135","tip":"135 (Sokak)"},{"id":592405,"il_id":33,"ilce_id":1892,"mahalle_id":182459,"ad":"136","tip":"136 (Sokak)"},{"id":591986,"il_id":33,"ilce_id":1892,"mahalle_id":182459,"ad":"137","tip":"137 (Sokak)"},{"id":599358,"il_id":33,"ilce_id":1892,"mahalle_id":182459,"ad":"138","tip":"138 (Sokak)"},{"id":748268,"il_id":33,"ilce_id":1892,"mahalle_id":182459,"ad":"139","tip":"139 (Sokak)"},{"id":367655,"il_id":33,"ilce_id":1892,"mahalle_id":182459,"ad":"14","tip":"14 (Sokak)"},{"id":440576100,"il_id":33,"ilce_id":1892,"mahalle_id":182459,"ad":"140","tip":"140 (Sokak)"},{"id":90309,"il_id":33,"ilce_id":1892,"mahalle_id":182459,"ad":"142","tip":"142 (Sokak)"},{"id":602272,"il_id":33,"ilce_id":1892,"mahalle_id":182459,"ad":"144","tip":"144 (Sokak)"},{"id":596645,"il_id":33,"ilce_id":1892,"mahalle_id":182459,"ad":"147","tip":"147 (Sokak)"},{"id":598384,"il_id":33,"ilce_id":1892,"mahalle_id":182459,"ad":"148","tip":"148 (Sokak)"},{"id":599373,"il_id":33,"ilce_id":1892,"mahalle_id":182459,"ad":"149","tip":"149 (Sokak)"},{"id":446123,"il_id":33,"ilce_id":1892,"mahalle_id":182459,"ad":"15","tip":"15 (Sokak)"},{"id":595396,"il_id":33,"ilce_id":1892,"mahalle_id":182459,"ad":"150","tip":"150 (Sokak)"},{"id":592789,"il_id":33,"ilce_id":1892,"mahalle_id":182459,"ad":"151","tip":"151 (Sokak)"},{"id":593657,"il_id":33,"ilce_id":1892,"mahalle_id":182459,"ad":"152","tip":"152 (Sokak)"},{"id":597548,"il_id":33,"ilce_id":1892,"mahalle_id":182459,"ad":"153","tip":"153 (Sokak)"},{"id":599377,"il_id":33,"ilce_id":1892,"mahalle_id":182459,"ad":"154","tip":"154 (Sokak)"},{"id":598386,"il_id":33,"ilce_id":1892,"mahalle_id":182459,"ad":"155","tip":"155 (Sokak)"},{"id":592790,"il_id":33,"ilce_id":1892,"mahalle_id":182459,"ad":"157","tip":"157 (Sokak)"},{"id":591990,"il_id":33,"ilce_id":1892,"mahalle_id":182459,"ad":"158","tip":"158 (Sokak)"},{"id":593682,"il_id":33,"ilce_id":1892,"mahalle_id":182459,"ad":"159","tip":"159 (Sokak)"},{"id":364700,"il_id":33,"ilce_id":1892,"mahalle_id":182459,"ad":"16","tip":"16 (Sokak)"},{"id":594552,"il_id":33,"ilce_id":1892,"mahalle_id":182459,"ad":"160","tip":"160 (Sokak)"},{"id":593242,"il_id":33,"ilce_id":1892,"mahalle_id":182459,"ad":"161","tip":"161 (Sokak)"},{"id":594467,"il_id":33,"ilce_id":1892,"mahalle_id":182459,"ad":"163","tip":"163 (Sokak)"},{"id":595398,"il_id":33,"ilce_id":1892,"mahalle_id":182459,"ad":"164","tip":"164 (Sokak)"},{"id":591991,"il_id":33,"ilce_id":1892,"mahalle_id":182459,"ad":"166","tip":"166 (Sokak)"},{"id":595767,"il_id":33,"ilce_id":1892,"mahalle_id":182459,"ad":"167-","tip":"167- (Sokak)"},{"id":595400,"il_id":33,"ilce_id":1892,"mahalle_id":182459,"ad":"169","tip":"169 (Sokak)"},{"id":369674,"il_id":33,"ilce_id":1892,"mahalle_id":182459,"ad":"17","tip":"17 (Sokak)"},{"id":596655,"il_id":33,"ilce_id":1892,"mahalle_id":182459,"ad":"170","tip":"170 (Sokak)"},{"id":593247,"il_id":33,"ilce_id":1892,"mahalle_id":182459,"ad":"171","tip":"171 (Sokak)"},{"id":595769,"il_id":33,"ilce_id":1892,"mahalle_id":182459,"ad":"172","tip":"172 (Sokak)"},{"id":591992,"il_id":33,"ilce_id":1892,"mahalle_id":182459,"ad":"174","tip":"174 (Sokak)"},{"id":596657,"il_id":33,"ilce_id":1892,"mahalle_id":182459,"ad":"176","tip":"176 (Sokak)"},{"id":593760,"il_id":33,"ilce_id":1892,"mahalle_id":182459,"ad":"177","tip":"177 (Sokak)"},{"id":595404,"il_id":33,"ilce_id":1892,"mahalle_id":182459,"ad":"178","tip":"178 (Sokak)"},{"id":367695,"il_id":33,"ilce_id":1892,"mahalle_id":182459,"ad":"18-","tip":"18- (Sokak)"},{"id":596659,"il_id":33,"ilce_id":1892,"mahalle_id":182459,"ad":"180","tip":"180 (Sokak)"},{"id":591994,"il_id":33,"ilce_id":1892,"mahalle_id":182459,"ad":"181","tip":"181 (Sokak)"},{"id":601825,"il_id":33,"ilce_id":1892,"mahalle_id":182459,"ad":"182","tip":"182 (Sokak)"},{"id":592411,"il_id":33,"ilce_id":1892,"mahalle_id":182459,"ad":"183","tip":"183 (Sokak)"},{"id":601378,"il_id":33,"ilce_id":1892,"mahalle_id":182459,"ad":"184","tip":"184 (Cadde)"},{"id":593762,"il_id":33,"ilce_id":1892,"mahalle_id":182459,"ad":"185","tip":"185 (Sokak)"},{"id":591997,"il_id":33,"ilce_id":1892,"mahalle_id":182459,"ad":"186","tip":"186 (Sokak)"},{"id":230732810,"il_id":33,"ilce_id":1892,"mahalle_id":182459,"ad":"187","tip":"187 (Sokak)"},{"id":601379,"il_id":33,"ilce_id":1892,"mahalle_id":182459,"ad":"189","tip":"189 (Sokak)"},{"id":552106,"il_id":33,"ilce_id":1892,"mahalle_id":182459,"ad":"19","tip":"19 (Sokak)"},{"id":594884,"il_id":33,"ilce_id":1892,"mahalle_id":182459,"ad":"190","tip":"190 (Sokak)"},{"id":597137,"il_id":33,"ilce_id":1892,"mahalle_id":182459,"ad":"191","tip":"191 (Sokak)"},{"id":241762,"il_id":33,"ilce_id":1892,"mahalle_id":182459,"ad":"192","tip":"192 (Sokak)"},{"id":602696,"il_id":33,"ilce_id":1892,"mahalle_id":182459,"ad":"194","tip":"194 (Sokak)"},{"id":596660,"il_id":33,"ilce_id":1892,"mahalle_id":182459,"ad":"195","tip":"195 (Sokak)"},{"id":598408,"il_id":33,"ilce_id":1892,"mahalle_id":182459,"ad":"196","tip":"196 (Sokak)"},{"id":675712,"il_id":33,"ilce_id":1892,"mahalle_id":182459,"ad":"199","tip":"199 (Sokak)"},{"id":550316,"il_id":33,"ilce_id":1892,"mahalle_id":182459,"ad":"2","tip":"2 (Sokak)"},{"id":364703,"il_id":33,"ilce_id":1892,"mahalle_id":182459,"ad":"20","tip":"20 (Sokak)"},{"id":597140,"il_id":33,"ilce_id":1892,"mahalle_id":182459,"ad":"201","tip":"201 (Sokak)"},{"id":593259,"il_id":33,"ilce_id":1892,"mahalle_id":182459,"ad":"202","tip":"202 (Sokak)"},{"id":596231,"il_id":33,"ilce_id":1892,"mahalle_id":182459,"ad":"203","tip":"203 (Sokak)"},{"id":592418,"il_id":33,"ilce_id":1892,"mahalle_id":182459,"ad":"204","tip":"204 (Sokak)"},{"id":603043,"il_id":33,"ilce_id":1892,"mahalle_id":182459,"ad":"205","tip":"205 (Sokak)"},{"id":592792,"il_id":33,"ilce_id":1892,"mahalle_id":182459,"ad":"207","tip":"207 (Sokak)"},{"id":594886,"il_id":33,"ilce_id":1892,"mahalle_id":182459,"ad":"209","tip":"209 (Sokak)"},{"id":369676,"il_id":33,"ilce_id":1892,"mahalle_id":182459,"ad":"21","tip":"21 (Sokak)"},{"id":594193,"il_id":33,"ilce_id":1892,"mahalle_id":182459,"ad":"210","tip":"210 (Sokak)"},{"id":603045,"il_id":33,"ilce_id":1892,"mahalle_id":182459,"ad":"211-","tip":"211- (Sokak)"},{"id":601828,"il_id":33,"ilce_id":1892,"mahalle_id":182459,"ad":"212-","tip":"212- (Sokak)"},{"id":680011,"il_id":33,"ilce_id":1892,"mahalle_id":182459,"ad":"213","tip":"213 (Sokak)"},{"id":466598840,"il_id":33,"ilce_id":1892,"mahalle_id":182459,"ad":"213/1","tip":"213/1 (Sokak)"},{"id":592005,"il_id":33,"ilce_id":1892,"mahalle_id":182459,"ad":"214","tip":"214 (Sokak)"},{"id":674955,"il_id":33,"ilce_id":1892,"mahalle_id":182459,"ad":"215","tip":"215 (Sokak)"},{"id":593264,"il_id":33,"ilce_id":1892,"mahalle_id":182459,"ad":"217 -","tip":"217 - (Sokak)"},{"id":675757,"il_id":33,"ilce_id":1892,"mahalle_id":182459,"ad":"218","tip":"218 (Sokak)"},{"id":354692,"il_id":33,"ilce_id":1892,"mahalle_id":182459,"ad":"22-","tip":"22- (Sokak)"},{"id":677089,"il_id":33,"ilce_id":1892,"mahalle_id":182459,"ad":"222","tip":"222 (Sokak)"},{"id":271709,"il_id":33,"ilce_id":1892,"mahalle_id":182459,"ad":"223","tip":"223 (Sokak)"},{"id":594889,"il_id":33,"ilce_id":1892,"mahalle_id":182459,"ad":"224","tip":"224 (Sokak)"},{"id":598413,"il_id":33,"ilce_id":1892,"mahalle_id":182459,"ad":"225","tip":"225 (Sokak)"},{"id":592794,"il_id":33,"ilce_id":1892,"mahalle_id":182459,"ad":"226","tip":"226 (Sokak)"},{"id":675005,"il_id":33,"ilce_id":1892,"mahalle_id":182459,"ad":"227","tip":"227 (Sokak)"},{"id":395187,"il_id":33,"ilce_id":1892,"mahalle_id":182459,"ad":"228","tip":"228 (Sokak)"},{"id":675760,"il_id":33,"ilce_id":1892,"mahalle_id":182459,"ad":"229-","tip":"229- (Sokak)"},{"id":446128,"il_id":33,"ilce_id":1892,"mahalle_id":182459,"ad":"23","tip":"23 (Sokak)"},{"id":636556,"il_id":33,"ilce_id":1892,"mahalle_id":182459,"ad":"230","tip":"230 (Sokak)"},{"id":593604,"il_id":33,"ilce_id":1892,"mahalle_id":182459,"ad":"231","tip":"231 (Sokak)"},{"id":91271,"il_id":33,"ilce_id":1892,"mahalle_id":182459,"ad":"232","tip":"232 (Sokak)"},{"id":592796,"il_id":33,"ilce_id":1892,"mahalle_id":182459,"ad":"233","tip":"233 (Sokak)"},{"id":177115,"il_id":33,"ilce_id":1892,"mahalle_id":182459,"ad":"234","tip":"234 (Sokak)"},{"id":177473,"il_id":33,"ilce_id":1892,"mahalle_id":182459,"ad":"236-","tip":"236- (Sokak)"},{"id":601832,"il_id":33,"ilce_id":1892,"mahalle_id":182459,"ad":"237","tip":"237 (Sokak)"},{"id":177476,"il_id":33,"ilce_id":1892,"mahalle_id":182459,"ad":"238","tip":"238 (Sokak)"},{"id":675763,"il_id":33,"ilce_id":1892,"mahalle_id":182459,"ad":"239","tip":"239 (Sokak)"},{"id":269148,"il_id":33,"ilce_id":1892,"mahalle_id":182459,"ad":"24","tip":"24 (Sokak)"},{"id":639064,"il_id":33,"ilce_id":1892,"mahalle_id":182459,"ad":"240","tip":"240 (Sokak)"},{"id":674451,"il_id":33,"ilce_id":1892,"mahalle_id":182459,"ad":"241","tip":"241 (Sokak)"},{"id":177505,"il_id":33,"ilce_id":1892,"mahalle_id":182459,"ad":"244","tip":"244 (Sokak)"},{"id":596243,"il_id":33,"ilce_id":1892,"mahalle_id":182459,"ad":"245","tip":"245 (Sokak)"},{"id":593664,"il_id":33,"ilce_id":1892,"mahalle_id":182459,"ad":"247","tip":"247 (Sokak)"},{"id":637581,"il_id":33,"ilce_id":1892,"mahalle_id":182459,"ad":"248","tip":"248 (Sokak)"},{"id":265354,"il_id":33,"ilce_id":1892,"mahalle_id":182459,"ad":"25","tip":"25 (Sokak)"},{"id":177509,"il_id":33,"ilce_id":1892,"mahalle_id":182459,"ad":"250","tip":"250 (Sokak)"},{"id":177531,"il_id":33,"ilce_id":1892,"mahalle_id":182459,"ad":"252","tip":"252 (Sokak)"},{"id":635094,"il_id":33,"ilce_id":1892,"mahalle_id":182459,"ad":"253","tip":"253 (Sokak)"},{"id":633851,"il_id":33,"ilce_id":1892,"mahalle_id":182459,"ad":"254","tip":"254 (Sokak)"},{"id":636024,"il_id":33,"ilce_id":1892,"mahalle_id":182459,"ad":"255","tip":"255 (Sokak)"},{"id":638207,"il_id":33,"ilce_id":1892,"mahalle_id":182459,"ad":"256","tip":"256 (Sokak)"},{"id":635387,"il_id":33,"ilce_id":1892,"mahalle_id":182459,"ad":"257","tip":"257 (Sokak)"},{"id":633852,"il_id":33,"ilce_id":1892,"mahalle_id":182459,"ad":"258","tip":"258 (Sokak)"},{"id":637408,"il_id":33,"ilce_id":1892,"mahalle_id":182459,"ad":"259","tip":"259 (Sokak)"},{"id":364704,"il_id":33,"ilce_id":1892,"mahalle_id":182459,"ad":"26","tip":"26 (Sokak)"},{"id":637410,"il_id":33,"ilce_id":1892,"mahalle_id":182459,"ad":"260","tip":"260 (Sokak)"},{"id":633855,"il_id":33,"ilce_id":1892,"mahalle_id":182459,"ad":"261","tip":"261 (Sokak)"},{"id":639242,"il_id":33,"ilce_id":1892,"mahalle_id":182459,"ad":"262","tip":"262 (Sokak)"},{"id":630001,"il_id":33,"ilce_id":1892,"mahalle_id":182459,"ad":"263","tip":"263 (Sokak)"},{"id":635095,"il_id":33,"ilce_id":1892,"mahalle_id":182459,"ad":"264","tip":"264 (Sokak)"},{"id":637317,"il_id":33,"ilce_id":1892,"mahalle_id":182459,"ad":"265","tip":"265 (Sokak)"},{"id":632974,"il_id":33,"ilce_id":1892,"mahalle_id":182459,"ad":"266","tip":"266 (Sokak)"},{"id":635390,"il_id":33,"ilce_id":1892,"mahalle_id":182459,"ad":"267","tip":"267 (Sokak)"},{"id":633860,"il_id":33,"ilce_id":1892,"mahalle_id":182459,"ad":"269","tip":"269 (Sokak)"},{"id":550326,"il_id":33,"ilce_id":1892,"mahalle_id":182459,"ad":"27","tip":"27 (Sokak)"},{"id":634805,"il_id":33,"ilce_id":1892,"mahalle_id":182459,"ad":"271","tip":"271 (Sokak)"},{"id":639068,"il_id":33,"ilce_id":1892,"mahalle_id":182459,"ad":"275","tip":"275 (Sokak)"},{"id":632979,"il_id":33,"ilce_id":1892,"mahalle_id":182459,"ad":"276","tip":"276 (Sokak)"},{"id":449590,"il_id":33,"ilce_id":1892,"mahalle_id":182459,"ad":"28","tip":"28 (Sokak)"},{"id":635396,"il_id":33,"ilce_id":1892,"mahalle_id":182459,"ad":"281","tip":"281 (Sokak)"},{"id":635398,"il_id":33,"ilce_id":1892,"mahalle_id":182459,"ad":"282","tip":"282 (Sokak)"},{"id":634808,"il_id":33,"ilce_id":1892,"mahalle_id":182459,"ad":"283","tip":"283 (Sokak)"},{"id":639074,"il_id":33,"ilce_id":1892,"mahalle_id":182459,"ad":"284","tip":"284 (Sokak)"},{"id":639255,"il_id":33,"ilce_id":1892,"mahalle_id":182459,"ad":"285","tip":"285 (Sokak)"},{"id":639256,"il_id":33,"ilce_id":1892,"mahalle_id":182459,"ad":"286","tip":"286 (Sokak)"},{"id":639075,"il_id":33,"ilce_id":1892,"mahalle_id":182459,"ad":"287","tip":"287 (Sokak)"},{"id":636041,"il_id":33,"ilce_id":1892,"mahalle_id":182459,"ad":"289-","tip":"289- (Sokak)"},{"id":638937,"il_id":33,"ilce_id":1892,"mahalle_id":182459,"ad":"290","tip":"290 (Sokak)"},{"id":637769,"il_id":33,"ilce_id":1892,"mahalle_id":182459,"ad":"291","tip":"291 (Sokak)"},{"id":638938,"il_id":33,"ilce_id":1892,"mahalle_id":182459,"ad":"292","tip":"292 (Sokak)"},{"id":638598,"il_id":33,"ilce_id":1892,"mahalle_id":182459,"ad":"293","tip":"293 (Sokak)"},{"id":630013,"il_id":33,"ilce_id":1892,"mahalle_id":182459,"ad":"294","tip":"294 (Sokak)"},{"id":637590,"il_id":33,"ilce_id":1892,"mahalle_id":182459,"ad":"296","tip":"296 (Sokak)"},{"id":634752,"il_id":33,"ilce_id":1892,"mahalle_id":182459,"ad":"297","tip":"297 (Sokak)"},{"id":636044,"il_id":33,"ilce_id":1892,"mahalle_id":182459,"ad":"299","tip":"299 (Sokak)"},{"id":552101,"il_id":33,"ilce_id":1892,"mahalle_id":182459,"ad":"3","tip":"3 (Sokak)"},{"id":450757,"il_id":33,"ilce_id":1892,"mahalle_id":182459,"ad":"30","tip":"30 (Sokak)"},{"id":293324,"il_id":33,"ilce_id":1892,"mahalle_id":182459,"ad":"301-","tip":"301- (Sokak)"},{"id":293319,"il_id":33,"ilce_id":1892,"mahalle_id":182459,"ad":"302","tip":"302 (Sokak)"},{"id":293325,"il_id":33,"ilce_id":1892,"mahalle_id":182459,"ad":"303","tip":"303 (Sokak)"},{"id":654132,"il_id":33,"ilce_id":1892,"mahalle_id":182459,"ad":"307","tip":"307 (Sokak)"},{"id":653684,"il_id":33,"ilce_id":1892,"mahalle_id":182459,"ad":"309","tip":"309 (Sokak)"},{"id":653687,"il_id":33,"ilce_id":1892,"mahalle_id":182459,"ad":"311","tip":"311 (Sokak)"},{"id":649013,"il_id":33,"ilce_id":1892,"mahalle_id":182459,"ad":"312-","tip":"312- (Sokak)"},{"id":659236,"il_id":33,"ilce_id":1892,"mahalle_id":182459,"ad":"313","tip":"313 (Sokak)"},{"id":649019,"il_id":33,"ilce_id":1892,"mahalle_id":182459,"ad":"314","tip":"314 (Sokak)"},{"id":659240,"il_id":33,"ilce_id":1892,"mahalle_id":182459,"ad":"315-","tip":"315- (Sokak)"},{"id":658078,"il_id":33,"ilce_id":1892,"mahalle_id":182459,"ad":"317","tip":"317 (Sokak)"},{"id":328204580,"il_id":33,"ilce_id":1892,"mahalle_id":182459,"ad":"317/1","tip":"317/1 (Sokak)"},{"id":530839110,"il_id":33,"ilce_id":1892,"mahalle_id":182459,"ad":"317/2","tip":"317/2 (Sokak)"},{"id":265359,"il_id":33,"ilce_id":1892,"mahalle_id":182459,"ad":"32","tip":"32 (Sokak)"},{"id":659251,"il_id":33,"ilce_id":1892,"mahalle_id":182459,"ad":"324","tip":"324 (Sokak)"},{"id":647685,"il_id":33,"ilce_id":1892,"mahalle_id":182459,"ad":"326","tip":"326 (Sokak)"},{"id":655863,"il_id":33,"ilce_id":1892,"mahalle_id":182459,"ad":"329","tip":"329 (Sokak)"},{"id":335923120,"il_id":33,"ilce_id":1892,"mahalle_id":182459,"ad":"329/1","tip":"329/1 (Sokak)"},{"id":449931,"il_id":33,"ilce_id":1892,"mahalle_id":182459,"ad":"33","tip":"33 (Sokak)"},{"id":839109760,"il_id":33,"ilce_id":1892,"mahalle_id":182459,"ad":"33/1","tip":"33/1 (Sokak)"},{"id":882789990,"il_id":33,"ilce_id":1892,"mahalle_id":182459,"ad":"33/2","tip":"33/2 (Sokak)"},{"id":649040,"il_id":33,"ilce_id":1892,"mahalle_id":182459,"ad":"335","tip":"335 (Sokak)"},{"id":658038,"il_id":33,"ilce_id":1892,"mahalle_id":182459,"ad":"341","tip":"341 (Sokak)"},{"id":161867,"il_id":33,"ilce_id":1892,"mahalle_id":182459,"ad":"355","tip":"355 (Sokak)"},{"id":721511940,"il_id":33,"ilce_id":1892,"mahalle_id":182459,"ad":"36","tip":"36 (Sokak)"},{"id":663276,"il_id":33,"ilce_id":1892,"mahalle_id":182459,"ad":"363","tip":"363 (Sokak)"},{"id":664028,"il_id":33,"ilce_id":1892,"mahalle_id":182459,"ad":"365","tip":"365 (Sokak)"},{"id":449932,"il_id":33,"ilce_id":1892,"mahalle_id":182459,"ad":"37","tip":"37 (Sokak)"},{"id":386166,"il_id":33,"ilce_id":1892,"mahalle_id":182459,"ad":"379-","tip":"379- (Sokak)"},{"id":262073,"il_id":33,"ilce_id":1892,"mahalle_id":182459,"ad":"38","tip":"38 (Sokak)"},{"id":665769,"il_id":33,"ilce_id":1892,"mahalle_id":182459,"ad":"389-","tip":"389- (Sokak)"},{"id":547374,"il_id":33,"ilce_id":1892,"mahalle_id":182459,"ad":"39","tip":"39 (Sokak)"},{"id":254769,"il_id":33,"ilce_id":1892,"mahalle_id":182459,"ad":"394-","tip":"394- (Sokak)"},{"id":665774,"il_id":33,"ilce_id":1892,"mahalle_id":182459,"ad":"396-","tip":"396- (Sokak)"},{"id":92347,"il_id":33,"ilce_id":1892,"mahalle_id":182459,"ad":"398","tip":"398 (Sokak)"},{"id":546051,"il_id":33,"ilce_id":1892,"mahalle_id":182459,"ad":"4","tip":"4 (Sokak)"},{"id":370918,"il_id":33,"ilce_id":1892,"mahalle_id":182459,"ad":"40","tip":"40 (Sokak)"},{"id":665781,"il_id":33,"ilce_id":1892,"mahalle_id":182459,"ad":"400","tip":"400 (Sokak)"},{"id":671283,"il_id":33,"ilce_id":1892,"mahalle_id":182459,"ad":"402-","tip":"402- (Sokak)"},{"id":671284,"il_id":33,"ilce_id":1892,"mahalle_id":182459,"ad":"404-","tip":"404- (Sokak)"},{"id":672863,"il_id":33,"ilce_id":1892,"mahalle_id":182459,"ad":"406","tip":"406 (Sokak)"},{"id":670842,"il_id":33,"ilce_id":1892,"mahalle_id":182459,"ad":"408","tip":"408 (Sokak)"},{"id":552109,"il_id":33,"ilce_id":1892,"mahalle_id":182459,"ad":"41","tip":"41 (Sokak)"},{"id":671384,"il_id":33,"ilce_id":1892,"mahalle_id":182459,"ad":"410","tip":"410 (Sokak)"},{"id":668986,"il_id":33,"ilce_id":1892,"mahalle_id":182459,"ad":"412-","tip":"412- (Sokak)"},{"id":669719,"il_id":33,"ilce_id":1892,"mahalle_id":182459,"ad":"416","tip":"416 (Sokak)"},{"id":667406,"il_id":33,"ilce_id":1892,"mahalle_id":182459,"ad":"418","tip":"418 (Sokak)"},{"id":354694,"il_id":33,"ilce_id":1892,"mahalle_id":182459,"ad":"42","tip":"42 (Sokak)"},{"id":673943,"il_id":33,"ilce_id":1892,"mahalle_id":182459,"ad":"420","tip":"420 (Sokak)"},{"id":671288,"il_id":33,"ilce_id":1892,"mahalle_id":182459,"ad":"422","tip":"422 (Sokak)"},{"id":669784,"il_id":33,"ilce_id":1892,"mahalle_id":182459,"ad":"424","tip":"424 (Sokak)"},{"id":668991,"il_id":33,"ilce_id":1892,"mahalle_id":182459,"ad":"426","tip":"426 (Sokak)"},{"id":670849,"il_id":33,"ilce_id":1892,"mahalle_id":182459,"ad":"428","tip":"428 (Sokak)"},{"id":265362,"il_id":33,"ilce_id":1892,"mahalle_id":182459,"ad":"43","tip":"43 (Sokak)"},{"id":672870,"il_id":33,"ilce_id":1892,"mahalle_id":182459,"ad":"430","tip":"430 (Sokak)"},{"id":672874,"il_id":33,"ilce_id":1892,"mahalle_id":182459,"ad":"432","tip":"432 (Sokak)"},{"id":671108,"il_id":33,"ilce_id":1892,"mahalle_id":182459,"ad":"434","tip":"434 (Sokak)"},{"id":669793,"il_id":33,"ilce_id":1892,"mahalle_id":182459,"ad":"436","tip":"436 (Sokak)"},{"id":669794,"il_id":33,"ilce_id":1892,"mahalle_id":182459,"ad":"438","tip":"438 (Sokak)"},{"id":265363,"il_id":33,"ilce_id":1892,"mahalle_id":182459,"ad":"44-","tip":"44- (Sokak)"},{"id":669795,"il_id":33,"ilce_id":1892,"mahalle_id":182459,"ad":"440","tip":"440 (Sokak)"},{"id":671115,"il_id":33,"ilce_id":1892,"mahalle_id":182459,"ad":"442","tip":"442 (Sokak)"},{"id":672882,"il_id":33,"ilce_id":1892,"mahalle_id":182459,"ad":"443-","tip":"443- (Sokak)"},{"id":671295,"il_id":33,"ilce_id":1892,"mahalle_id":182459,"ad":"444","tip":"444 (Sokak)"},{"id":671297,"il_id":33,"ilce_id":1892,"mahalle_id":182459,"ad":"446","tip":"446 (Sokak)"},{"id":671118,"il_id":33,"ilce_id":1892,"mahalle_id":182459,"ad":"447","tip":"447 (Sokak)"},{"id":671298,"il_id":33,"ilce_id":1892,"mahalle_id":182459,"ad":"448","tip":"448 (Sokak)"},{"id":670603,"il_id":33,"ilce_id":1892,"mahalle_id":182459,"ad":"449-","tip":"449- (Sokak)"},{"id":364712,"il_id":33,"ilce_id":1892,"mahalle_id":182459,"ad":"45","tip":"45 (Sokak)"},{"id":669797,"il_id":33,"ilce_id":1892,"mahalle_id":182459,"ad":"450","tip":"450 (Sokak)"},{"id":287173950,"il_id":33,"ilce_id":1892,"mahalle_id":182459,"ad":"450/1","tip":"450/1 (Sokak)"},{"id":669798,"il_id":33,"ilce_id":1892,"mahalle_id":182459,"ad":"451-","tip":"451- (Sokak)"},{"id":671299,"il_id":33,"ilce_id":1892,"mahalle_id":182459,"ad":"452","tip":"452 (Sokak)"},{"id":671300,"il_id":33,"ilce_id":1892,"mahalle_id":182459,"ad":"453","tip":"453 (Sokak)"},{"id":670605,"il_id":33,"ilce_id":1892,"mahalle_id":182459,"ad":"454","tip":"454 (Sokak)"},{"id":671121,"il_id":33,"ilce_id":1892,"mahalle_id":182459,"ad":"455","tip":"455 (Sokak)"},{"id":669722,"il_id":33,"ilce_id":1892,"mahalle_id":182459,"ad":"457","tip":"457 (Sokak)"},{"id":669802,"il_id":33,"ilce_id":1892,"mahalle_id":182459,"ad":"458","tip":"458 (Sokak)"},{"id":670608,"il_id":33,"ilce_id":1892,"mahalle_id":182459,"ad":"459","tip":"459 (Sokak)"},{"id":670609,"il_id":33,"ilce_id":1892,"mahalle_id":182459,"ad":"460","tip":"460 (Sokak)"},{"id":667893,"il_id":33,"ilce_id":1892,"mahalle_id":182459,"ad":"461","tip":"461 (Sokak)"},{"id":672202,"il_id":33,"ilce_id":1892,"mahalle_id":182459,"ad":"462","tip":"462 (Sokak)"},{"id":667749,"il_id":33,"ilce_id":1892,"mahalle_id":182459,"ad":"463","tip":"463 (Sokak)"},{"id":672207,"il_id":33,"ilce_id":1892,"mahalle_id":182459,"ad":"464","tip":"464 (Sokak)"},{"id":672211,"il_id":33,"ilce_id":1892,"mahalle_id":182459,"ad":"465","tip":"465 (Sokak)"},{"id":672215,"il_id":33,"ilce_id":1892,"mahalle_id":182459,"ad":"466","tip":"466 (Sokak)"},{"id":227857780,"il_id":33,"ilce_id":1892,"mahalle_id":182459,"ad":"466/1","tip":"466/1 (Sokak)"},{"id":417926491,"il_id":33,"ilce_id":1892,"mahalle_id":31910,"ad":"466/1","tip":"466/1 (Sokak)"},{"id":672218,"il_id":33,"ilce_id":1892,"mahalle_id":182459,"ad":"467","tip":"467 (Sokak)"},{"id":672221,"il_id":33,"ilce_id":1892,"mahalle_id":182459,"ad":"468","tip":"468 (Sokak)"},{"id":672228,"il_id":33,"ilce_id":1892,"mahalle_id":182459,"ad":"469","tip":"469 (Sokak)"},{"id":364715,"il_id":33,"ilce_id":1892,"mahalle_id":182459,"ad":"47","tip":"47 (Sokak)"},{"id":672233,"il_id":33,"ilce_id":1892,"mahalle_id":182459,"ad":"470","tip":"470 (Sokak)"},{"id":669409,"il_id":33,"ilce_id":1892,"mahalle_id":182459,"ad":"471-","tip":"471- (Sokak)"},{"id":667629,"il_id":33,"ilce_id":1892,"mahalle_id":182459,"ad":"473-","tip":"473- (Sokak)"},{"id":667634,"il_id":33,"ilce_id":1892,"mahalle_id":182459,"ad":"475","tip":"475 (Sokak)"},{"id":667643,"il_id":33,"ilce_id":1892,"mahalle_id":182459,"ad":"477","tip":"477 (Sokak)"},{"id":667382,"il_id":33,"ilce_id":1892,"mahalle_id":182459,"ad":"479","tip":"479 (Sokak)"},{"id":667653,"il_id":33,"ilce_id":1892,"mahalle_id":182459,"ad":"481","tip":"481 (Sokak)"},{"id":241151800,"il_id":33,"ilce_id":1892,"mahalle_id":182459,"ad":"481/1","tip":"481/1 (Sokak)"},{"id":667659,"il_id":33,"ilce_id":1892,"mahalle_id":182459,"ad":"483","tip":"483 (Sokak)"},{"id":667663,"il_id":33,"ilce_id":1892,"mahalle_id":182459,"ad":"485","tip":"485 (Sokak)"},{"id":667671,"il_id":33,"ilce_id":1892,"mahalle_id":182459,"ad":"487","tip":"487 (Sokak)"},{"id":667387,"il_id":33,"ilce_id":1892,"mahalle_id":182459,"ad":"489","tip":"489 (Sokak)"},{"id":146178980,"il_id":33,"ilce_id":1892,"mahalle_id":182459,"ad":"49","tip":"49 (Sokak)"},{"id":667681,"il_id":33,"ilce_id":1892,"mahalle_id":182459,"ad":"491","tip":"491 (Sokak)"},{"id":669414,"il_id":33,"ilce_id":1892,"mahalle_id":182459,"ad":"493","tip":"493 (Sokak)"},{"id":669422,"il_id":33,"ilce_id":1892,"mahalle_id":182459,"ad":"495","tip":"495 (Sokak)"},{"id":669763,"il_id":33,"ilce_id":1892,"mahalle_id":182459,"ad":"499","tip":"499 (Sokak)"},{"id":547370,"il_id":33,"ilce_id":1892,"mahalle_id":182459,"ad":"5","tip":"5 (Sokak)"},{"id":550858,"il_id":33,"ilce_id":1892,"mahalle_id":182459,"ad":"50","tip":"50 (Sokak)"},{"id":669766,"il_id":33,"ilce_id":1892,"mahalle_id":182459,"ad":"501","tip":"501 (Sokak)"},{"id":669770,"il_id":33,"ilce_id":1892,"mahalle_id":182459,"ad":"503","tip":"503 (Sokak)"},{"id":667394,"il_id":33,"ilce_id":1892,"mahalle_id":182459,"ad":"505","tip":"505 (Sokak)"},{"id":667399,"il_id":33,"ilce_id":1892,"mahalle_id":182459,"ad":"507","tip":"507 (Sokak)"},{"id":676083,"il_id":33,"ilce_id":1892,"mahalle_id":182459,"ad":"509","tip":"509 (Sokak)"},{"id":262571,"il_id":33,"ilce_id":1892,"mahalle_id":182459,"ad":"51","tip":"51 (Sokak)"},{"id":677892,"il_id":33,"ilce_id":1892,"mahalle_id":182459,"ad":"511","tip":"511 (Sokak)"},{"id":677893,"il_id":33,"ilce_id":1892,"mahalle_id":182459,"ad":"513","tip":"513 (Sokak)"},{"id":678537,"il_id":33,"ilce_id":1892,"mahalle_id":182459,"ad":"515","tip":"515 (Sokak)"},{"id":676758,"il_id":33,"ilce_id":1892,"mahalle_id":182459,"ad":"517","tip":"517 (Sokak)"},{"id":676760,"il_id":33,"ilce_id":1892,"mahalle_id":182459,"ad":"519","tip":"519 (Sokak)"},{"id":450758,"il_id":33,"ilce_id":1892,"mahalle_id":182459,"ad":"52","tip":"52 (Sokak)"},{"id":684412,"il_id":33,"ilce_id":1892,"mahalle_id":182459,"ad":"521","tip":"521 (Sokak)"},{"id":684413,"il_id":33,"ilce_id":1892,"mahalle_id":182459,"ad":"523","tip":"523 (Sokak)"},{"id":676761,"il_id":33,"ilce_id":1892,"mahalle_id":182459,"ad":"525-","tip":"525- (Sokak)"},{"id":676762,"il_id":33,"ilce_id":1892,"mahalle_id":182459,"ad":"527","tip":"527 (Sokak)"},{"id":267493,"il_id":33,"ilce_id":1892,"mahalle_id":182459,"ad":"53","tip":"53 (Sokak)"},{"id":446213,"il_id":33,"ilce_id":1892,"mahalle_id":182459,"ad":"54","tip":"54 (Sokak)"},{"id":550863,"il_id":33,"ilce_id":1892,"mahalle_id":182459,"ad":"56","tip":"56 (Sokak)"},{"id":450759,"il_id":33,"ilce_id":1892,"mahalle_id":182459,"ad":"57","tip":"57 (Sokak)"},{"id":262088,"il_id":33,"ilce_id":1892,"mahalle_id":182459,"ad":"59","tip":"59 (Sokak)"},{"id":399293690,"il_id":33,"ilce_id":1892,"mahalle_id":182459,"ad":"59/1","tip":"59/1 (Sokak)"},{"id":262093,"il_id":33,"ilce_id":1892,"mahalle_id":182459,"ad":"60","tip":"60 (Sokak)"},{"id":361918,"il_id":33,"ilce_id":1892,"mahalle_id":182459,"ad":"61","tip":"61 (Sokak)"},{"id":449952,"il_id":33,"ilce_id":1892,"mahalle_id":182459,"ad":"64","tip":"64 (Sokak)"},{"id":543919,"il_id":33,"ilce_id":1892,"mahalle_id":182459,"ad":"65","tip":"65 (Sokak)"},{"id":269161,"il_id":33,"ilce_id":1892,"mahalle_id":182459,"ad":"66","tip":"66 (Sokak)"},{"id":264166,"il_id":33,"ilce_id":1892,"mahalle_id":182459,"ad":"67","tip":"67 (Sokak)"},{"id":543923,"il_id":33,"ilce_id":1892,"mahalle_id":182459,"ad":"68","tip":"68 (Sokak)"},{"id":264167,"il_id":33,"ilce_id":1892,"mahalle_id":182459,"ad":"69","tip":"69 (Sokak)"},{"id":553891,"il_id":33,"ilce_id":1892,"mahalle_id":182459,"ad":"7","tip":"7 (Sokak)"},{"id":450008,"il_id":33,"ilce_id":1892,"mahalle_id":182459,"ad":"70","tip":"70 (Sokak)"},{"id":543927,"il_id":33,"ilce_id":1892,"mahalle_id":182459,"ad":"71","tip":"71 (Sokak)"},{"id":450012,"il_id":33,"ilce_id":1892,"mahalle_id":182459,"ad":"72","tip":"72 (Sokak)"},{"id":450329,"il_id":33,"ilce_id":1892,"mahalle_id":182459,"ad":"76","tip":"76 (Sokak)"},{"id":364692,"il_id":33,"ilce_id":1892,"mahalle_id":182459,"ad":"8","tip":"8 (Sokak)"},{"id":450340,"il_id":33,"ilce_id":1892,"mahalle_id":182459,"ad":"81","tip":"81 (Sokak)"},{"id":269145,"il_id":33,"ilce_id":1892,"mahalle_id":182459,"ad":"9","tip":"9 (Sokak)"},{"id":552117,"il_id":33,"ilce_id":1892,"mahalle_id":182459,"ad":"93-","tip":"93- (Sokak)"},{"id":260937,"il_id":33,"ilce_id":1892,"mahalle_id":182459,"ad":"95","tip":"95 (Sokak)"},{"id":611511,"il_id":33,"ilce_id":1892,"mahalle_id":182459,"ad":"97","tip":"97 (Sokak)"},{"id":581945,"il_id":33,"ilce_id":1892,"mahalle_id":182459,"ad":"99","tip":"99 (Sokak)"},{"id":890921,"il_id":33,"ilce_id":1892,"mahalle_id":31911,"ad":"Abdurrezzak şEn","tip":"Abdurrezzak şEn (Sokak)"},{"id":357624,"il_id":33,"ilce_id":1892,"mahalle_id":31911,"ad":"Adalya","tip":"Adalya (Sokak)"},{"id":407108730,"il_id":33,"ilce_id":1892,"mahalle_id":31911,"ad":"Adalya/1","tip":"Adalya/1 (Sokak)"},{"id":419111400,"il_id":33,"ilce_id":1892,"mahalle_id":31911,"ad":"Adalya/2","tip":"Adalya/2 (Sokak)"},{"id":372473760,"il_id":33,"ilce_id":1892,"mahalle_id":31911,"ad":"Adalya/3","tip":"Adalya/3 (Sokak)"},{"id":357612,"il_id":33,"ilce_id":1892,"mahalle_id":31910,"ad":"Adanalılar","tip":"Adanalılar (Sokak)"},{"id":750164930,"il_id":33,"ilce_id":1892,"mahalle_id":31910,"ad":"Adanalılar/1","tip":"Adanalılar/1 (Sokak)"},{"id":728105750,"il_id":33,"ilce_id":1892,"mahalle_id":31910,"ad":"Adanalılar/2","tip":"Adanalılar/2 (Sokak)"},{"id":293378880,"il_id":33,"ilce_id":1892,"mahalle_id":31910,"ad":"Adanalılar/4","tip":"Adanalılar/4 (Sokak)"},{"id":509558300,"il_id":33,"ilce_id":1892,"mahalle_id":31910,"ad":"Adanalılar/5","tip":"Adanalılar/5 (Sokak)"},{"id":890920,"il_id":33,"ilce_id":1892,"mahalle_id":31911,"ad":"Adnan Eren","tip":"Adnan Eren (Sokak)"},{"id":357273,"il_id":33,"ilce_id":1892,"mahalle_id":31912,"ad":"Ahmet ışıK","tip":"Ahmet ışıK (Sokak)"},{"id":679827,"il_id":33,"ilce_id":1892,"mahalle_id":31911,"ad":"Akasya","tip":"Akasya (Sokak)"},{"id":685537,"il_id":33,"ilce_id":1892,"mahalle_id":31911,"ad":"Akdeniz","tip":"Akdeniz (Cadde)"},{"id":159615840,"il_id":33,"ilce_id":1892,"mahalle_id":31911,"ad":"Akdeniz/1","tip":"Akdeniz/1 (Sokak)"},{"id":434730570,"il_id":33,"ilce_id":1892,"mahalle_id":31911,"ad":"Akdeniz/2","tip":"Akdeniz/2 (Sokak)"},{"id":746546,"il_id":33,"ilce_id":1892,"mahalle_id":31911,"ad":"Akşemseddin","tip":"Akşemseddin (Sokak)"},{"id":472781,"il_id":33,"ilce_id":1892,"mahalle_id":31910,"ad":"Ali Sekitmez","tip":"Ali Sekitmez (Sokak)"},{"id":357613,"il_id":33,"ilce_id":1892,"mahalle_id":31910,"ad":"Altılar","tip":"Altılar (Sokak)"},{"id":439900,"il_id":33,"ilce_id":1892,"mahalle_id":31911,"ad":"Anafartalar","tip":"Anafartalar (Sokak)"},{"id":109873110,"il_id":33,"ilce_id":1892,"mahalle_id":31911,"ad":"Anafartalar/1","tip":"Anafartalar/1 (Sokak)"},{"id":357270,"il_id":33,"ilce_id":1892,"mahalle_id":31911,"ad":"Aptilağa","tip":"Aptilağa (Sokak)"},{"id":116310250,"il_id":33,"ilce_id":1892,"mahalle_id":31911,"ad":"Aptilağa/1","tip":"Aptilağa/1 (Sokak)"},{"id":472786,"il_id":33,"ilce_id":1892,"mahalle_id":31911,"ad":"Ara","tip":"Ara (Sokak)"},{"id":357626,"il_id":33,"ilce_id":1892,"mahalle_id":31911,"ad":"Ardıç","tip":"Ardıç (Sokak)"},{"id":357614,"il_id":33,"ilce_id":1892,"mahalle_id":31910,"ad":"Armutlu","tip":"Armutlu (Sokak)"},{"id":173746380,"il_id":33,"ilce_id":1892,"mahalle_id":31910,"ad":"Armutlu/1","tip":"Armutlu/1 (Sokak)"},{"id":357627,"il_id":33,"ilce_id":1892,"mahalle_id":31911,"ad":"Arıcılar","tip":"Arıcılar (Sokak)"},{"id":473570,"il_id":33,"ilce_id":1892,"mahalle_id":31911,"ad":"Asmalı","tip":"Asmalı (Sokak)"},{"id":467314,"il_id":33,"ilce_id":1892,"mahalle_id":182459,"ad":"Atatürk","tip":"Atatürk (Cadde)"},{"id":326565,"il_id":33,"ilce_id":1892,"mahalle_id":182459,"ad":"Atatürk (Camii)-","tip":"Atatürk (Camii)- (Cadde)"},{"id":605319,"il_id":33,"ilce_id":1892,"mahalle_id":182459,"ad":"Atatürk (Orta)-","tip":"Atatürk (Orta)- (Cadde)"},{"id":358933,"il_id":33,"ilce_id":1892,"mahalle_id":182459,"ad":"Atatürk (Taşlıekinlik)-","tip":"Atatürk (Taşlıekinlik)- (Cadde)"},{"id":456062250,"il_id":33,"ilce_id":1892,"mahalle_id":31911,"ad":"Atatürk/1","tip":"Atatürk/1 (Sokak)"},{"id":683617,"il_id":33,"ilce_id":1892,"mahalle_id":31911,"ad":"Atatürk_1","tip":"Atatürk_1 (Cadde)"},{"id":510541,"il_id":33,"ilce_id":1892,"mahalle_id":182463,"ad":"Atdağı","tip":"Atdağı (Küme Evler)"},{"id":357628,"il_id":33,"ilce_id":1892,"mahalle_id":31911,"ad":"Atmaca","tip":"Atmaca (Sokak)"},{"id":218179780,"il_id":33,"ilce_id":1892,"mahalle_id":31911,"ad":"Atmaca/1","tip":"Atmaca/1 (Sokak)"},{"id":357629,"il_id":33,"ilce_id":1892,"mahalle_id":31911,"ad":"Aydıncık","tip":"Aydıncık (Sokak)"},{"id":504240,"il_id":33,"ilce_id":1892,"mahalle_id":182477,"ad":"Aşağı","tip":"Aşağı (Küme Evler)"},{"id":742692,"il_id":33,"ilce_id":1892,"mahalle_id":31911,"ad":"Aşık Veysel","tip":"Aşık Veysel (Sokak)"},{"id":357546,"il_id":33,"ilce_id":1892,"mahalle_id":31910,"ad":"Badem","tip":"Badem (Sokak)"},{"id":357547,"il_id":33,"ilce_id":1892,"mahalle_id":31910,"ad":"Bahtiyar","tip":"Bahtiyar (Sokak)"},{"id":357549,"il_id":33,"ilce_id":1892,"mahalle_id":31910,"ad":"Bandırma Tepesi","tip":"Bandırma Tepesi (Sokak)"},{"id":409530850,"il_id":33,"ilce_id":1892,"mahalle_id":31910,"ad":"Bandırma Tepesi/1","tip":"Bandırma Tepesi/1 (Sokak)"},{"id":441679300,"il_id":33,"ilce_id":1892,"mahalle_id":31910,"ad":"Bandırma Tepesi/2","tip":"Bandırma Tepesi/2 (Sokak)"},{"id":742693,"il_id":33,"ilce_id":1892,"mahalle_id":31911,"ad":"Barbaros Hayrettin Paşa","tip":"Barbaros Hayrettin Paşa (Sokak)"},{"id":357274,"il_id":33,"ilce_id":1892,"mahalle_id":31912,"ad":"Bayır","tip":"Bayır (Sokak)"},{"id":357630,"il_id":33,"ilce_id":1892,"mahalle_id":31911,"ad":"Bağlar","tip":"Bağlar (Sokak)"},{"id":261471650,"il_id":33,"ilce_id":1892,"mahalle_id":31911,"ad":"Bağlar/1","tip":"Bağlar/1 (Sokak)"},{"id":463247780,"il_id":33,"ilce_id":1892,"mahalle_id":31911,"ad":"Bağlar/2","tip":"Bağlar/2 (Sokak)"},{"id":485309,"il_id":33,"ilce_id":1892,"mahalle_id":182461,"ad":"Bağçatağı","tip":"Bağçatağı (Küme Evler)"},{"id":357275,"il_id":33,"ilce_id":1892,"mahalle_id":31912,"ad":"Başak","tip":"Başak (Sokak)"},{"id":467293,"il_id":33,"ilce_id":1892,"mahalle_id":31912,"ad":"Benli Yusuf Sit.","tip":"Benli Yusuf Sit. (Küme Evler)"},{"id":473571,"il_id":33,"ilce_id":1892,"mahalle_id":31911,"ad":"Berber","tip":"Berber (Sokak)"},{"id":357631,"il_id":33,"ilce_id":1892,"mahalle_id":31911,"ad":"Beste","tip":"Beste (Sokak)"},{"id":357550,"il_id":33,"ilce_id":1892,"mahalle_id":31910,"ad":"Beyazevler","tip":"Beyazevler (Sokak)"},{"id":357276,"il_id":33,"ilce_id":1892,"mahalle_id":31912,"ad":"Beyler","tip":"Beyler (Sokak)"},{"id":357554,"il_id":33,"ilce_id":1892,"mahalle_id":31910,"ad":"Bilge","tip":"Bilge (Sokak)"},{"id":357261,"il_id":33,"ilce_id":1892,"mahalle_id":31911,"ad":"Bostan","tip":"Bostan (Sokak)"},{"id":357277,"il_id":33,"ilce_id":1892,"mahalle_id":31912,"ad":"Bostan_1","tip":"Bostan_1 (Sokak)"},{"id":357632,"il_id":33,"ilce_id":1892,"mahalle_id":31911,"ad":"Boymul","tip":"Boymul (Sokak)"},{"id":357551,"il_id":33,"ilce_id":1892,"mahalle_id":31910,"ad":"Boğazlayan","tip":"Boğazlayan (Sokak)"},{"id":473572,"il_id":33,"ilce_id":1892,"mahalle_id":31911,"ad":"Bucak","tip":"Bucak (Sokak)"},{"id":357278,"il_id":33,"ilce_id":1892,"mahalle_id":31912,"ad":"Buladan","tip":"Buladan (Sokak)"},{"id":357957,"il_id":33,"ilce_id":1892,"mahalle_id":31911,"ad":"Bursa","tip":"Bursa (Sokak)"},{"id":383926840,"il_id":33,"ilce_id":1892,"mahalle_id":31911,"ad":"Bursa/1","tip":"Bursa/1 (Sokak)"},{"id":401735100,"il_id":33,"ilce_id":1892,"mahalle_id":31911,"ad":"Bursa/2","tip":"Bursa/2 (Sokak)"},{"id":357552,"il_id":33,"ilce_id":1892,"mahalle_id":31910,"ad":"Bülbül","tip":"Bülbül (Sokak)"},{"id":357553,"il_id":33,"ilce_id":1892,"mahalle_id":31910,"ad":"Büyük","tip":"Büyük (Sokak)"},{"id":467294,"il_id":33,"ilce_id":1892,"mahalle_id":31912,"ad":"Büyük Kale","tip":"Büyük Kale (Sokak)"},{"id":136758140,"il_id":33,"ilce_id":1892,"mahalle_id":31910,"ad":"Büyük/1","tip":"Büyük/1 (Sokak)"},{"id":39108,"il_id":33,"ilce_id":1892,"mahalle_id":182465,"ad":"Cami","tip":"Cami (Küme Evler)"},{"id":357279,"il_id":33,"ilce_id":1892,"mahalle_id":31912,"ad":"Camii","tip":"Camii (Sokak)"},{"id":558438900,"il_id":33,"ilce_id":1892,"mahalle_id":31912,"ad":"Camii/1","tip":"Camii/1 (Sokak)"},{"id":496431,"il_id":33,"ilce_id":1892,"mahalle_id":182479,"ad":"Candere","tip":"Candere (Küme Evler)"},{"id":832927,"il_id":33,"ilce_id":1892,"mahalle_id":31910,"ad":"Cennet","tip":"Cennet (Sokak)"},{"id":357555,"il_id":33,"ilce_id":1892,"mahalle_id":31910,"ad":"Cevizli","tip":"Cevizli (Sokak)"},{"id":357280,"il_id":33,"ilce_id":1892,"mahalle_id":31912,"ad":"Cevizli Kaya","tip":"Cevizli Kaya (Sokak)"},{"id":357556,"il_id":33,"ilce_id":1892,"mahalle_id":31910,"ad":"Ceyhan","tip":"Ceyhan (Sokak)"},{"id":468592030,"il_id":33,"ilce_id":1892,"mahalle_id":31910,"ad":"Ceyhan/1","tip":"Ceyhan/1 (Sokak)"},{"id":347262400,"il_id":33,"ilce_id":1892,"mahalle_id":31910,"ad":"Ceyhan/2","tip":"Ceyhan/2 (Sokak)"},{"id":472757,"il_id":33,"ilce_id":1892,"mahalle_id":31910,"ad":"Ceylan-","tip":"Ceylan- (Sokak)"},{"id":357958,"il_id":33,"ilce_id":1892,"mahalle_id":31911,"ad":"Cin","tip":"Cin (Sokak)"},{"id":357558,"il_id":33,"ilce_id":1892,"mahalle_id":31910,"ad":"Cinci Oluğu","tip":"Cinci Oluğu (Sokak)"},{"id":357281,"il_id":33,"ilce_id":1892,"mahalle_id":31912,"ad":"Cuma","tip":"Cuma (Sokak)"},{"id":395272700,"il_id":33,"ilce_id":1892,"mahalle_id":31912,"ad":"Cuma/2","tip":"Cuma/2 (Sokak)"},{"id":357557,"il_id":33,"ilce_id":1892,"mahalle_id":31910,"ad":"Cumayakası","tip":"Cumayakası (Cadde)"},{"id":467295,"il_id":33,"ilce_id":1892,"mahalle_id":31912,"ad":"Cumayakası","tip":"Cumayakası (Cadde)"},{"id":705580770,"il_id":33,"ilce_id":1892,"mahalle_id":31910,"ad":"Cumayakası/1","tip":"Cumayakası/1 (Sokak)"},{"id":357282,"il_id":33,"ilce_id":1892,"mahalle_id":31912,"ad":"Cumhuriyet","tip":"Cumhuriyet (Meydan)"},{"id":742694,"il_id":33,"ilce_id":1892,"mahalle_id":31911,"ad":"Dadaloğlu","tip":"Dadaloğlu (Sokak)"},{"id":357283,"il_id":33,"ilce_id":1892,"mahalle_id":31912,"ad":"Dar","tip":"Dar (Sokak)"},{"id":504445,"il_id":33,"ilce_id":1892,"mahalle_id":182465,"ad":"Darıpınarı","tip":"Darıpınarı (Küme Evler)"},{"id":472758,"il_id":33,"ilce_id":1892,"mahalle_id":31910,"ad":"Dedetaş","tip":"Dedetaş (Sokak)"},{"id":780659430,"il_id":33,"ilce_id":1892,"mahalle_id":31910,"ad":"Dedetaş/1","tip":"Dedetaş/1 (Sokak)"},{"id":357559,"il_id":33,"ilce_id":1892,"mahalle_id":31910,"ad":"Demet","tip":"Demet (Sokak)"},{"id":467296,"il_id":33,"ilce_id":1892,"mahalle_id":31912,"ad":"Demirci","tip":"Demirci (Sokak)"},{"id":461963660,"il_id":33,"ilce_id":1892,"mahalle_id":31912,"ad":"Demirci/1","tip":"Demirci/1 (Sokak)"},{"id":121507690,"il_id":33,"ilce_id":1892,"mahalle_id":31912,"ad":"Demirci/2","tip":"Demirci/2 (Sokak)"},{"id":357284,"il_id":33,"ilce_id":1892,"mahalle_id":31912,"ad":"Demirtaş","tip":"Demirtaş (Sokak)"},{"id":543800190,"il_id":33,"ilce_id":1892,"mahalle_id":31912,"ad":"Demirtaş/1","tip":"Demirtaş/1 (Sokak)"},{"id":226627200,"il_id":33,"ilce_id":1892,"mahalle_id":31912,"ad":"Demirtaş/4","tip":"Demirtaş/4 (Sokak)"},{"id":357285,"il_id":33,"ilce_id":1892,"mahalle_id":31912,"ad":"Depo","tip":"Depo (Sokak)"},{"id":357286,"il_id":33,"ilce_id":1892,"mahalle_id":31912,"ad":"Dere","tip":"Dere (Sokak)"},{"id":467297,"il_id":33,"ilce_id":1892,"mahalle_id":31912,"ad":"Değirmen","tip":"Değirmen (Sokak)"},{"id":472759,"il_id":33,"ilce_id":1892,"mahalle_id":31910,"ad":"Dik","tip":"Dik (Sokak)"},{"id":743010,"il_id":33,"ilce_id":1892,"mahalle_id":31911,"ad":"Dumlupınar","tip":"Dumlupınar (Cadde)"},{"id":402043150,"il_id":33,"ilce_id":1892,"mahalle_id":31911,"ad":"Dumlupınar/1","tip":"Dumlupınar/1 (Sokak)"},{"id":357287,"il_id":33,"ilce_id":1892,"mahalle_id":31912,"ad":"Dutlu","tip":"Dutlu (Sokak)"},{"id":401330010,"il_id":33,"ilce_id":1892,"mahalle_id":31912,"ad":"Dutlu 1","tip":"Dutlu 1 (Sokak)"},{"id":357288,"il_id":33,"ilce_id":1892,"mahalle_id":31912,"ad":"Dölek","tip":"Dölek (Sokak)"},{"id":473573,"il_id":33,"ilce_id":1892,"mahalle_id":31911,"ad":"Dönemeç","tip":"Dönemeç (Sokak)"},{"id":357560,"il_id":33,"ilce_id":1892,"mahalle_id":31910,"ad":"Düz","tip":"Düz (Sokak)"},{"id":467298,"il_id":33,"ilce_id":1892,"mahalle_id":31912,"ad":"Düzalan","tip":"Düzalan (Sokak)"},{"id":743011,"il_id":33,"ilce_id":1892,"mahalle_id":31911,"ad":"Ege","tip":"Ege (Cadde)"},{"id":357289,"il_id":33,"ilce_id":1892,"mahalle_id":31912,"ad":"Egemenlik","tip":"Egemenlik (Cadde)"},{"id":473900670,"il_id":33,"ilce_id":1892,"mahalle_id":31912,"ad":"Egemenlik/1","tip":"Egemenlik/1 (Sokak)"},{"id":357561,"il_id":33,"ilce_id":1892,"mahalle_id":31910,"ad":"Elmalı","tip":"Elmalı (Sokak)"},{"id":708971780,"il_id":33,"ilce_id":1892,"mahalle_id":31910,"ad":"Elmalı/1","tip":"Elmalı/1 (Sokak)"},{"id":136906800,"il_id":33,"ilce_id":1892,"mahalle_id":31910,"ad":"Elmalı/2","tip":"Elmalı/2 (Sokak)"},{"id":357562,"il_id":33,"ilce_id":1892,"mahalle_id":31910,"ad":"Elvan","tip":"Elvan (Sokak)"},{"id":357269,"il_id":33,"ilce_id":1892,"mahalle_id":31911,"ad":"Emre","tip":"Emre (Sokak)"},{"id":357563,"il_id":33,"ilce_id":1892,"mahalle_id":31910,"ad":"Enis Hoca","tip":"Enis Hoca (Sokak)"},{"id":358913,"il_id":33,"ilce_id":1892,"mahalle_id":31911,"ad":"Erciyes","tip":"Erciyes (Sokak)"},{"id":358914,"il_id":33,"ilce_id":1892,"mahalle_id":31911,"ad":"Erdem","tip":"Erdem (Sokak)"},{"id":358915,"il_id":33,"ilce_id":1892,"mahalle_id":31911,"ad":"Erdemli","tip":"Erdemli (Sokak)"},{"id":357564,"il_id":33,"ilce_id":1892,"mahalle_id":31910,"ad":"Erenler","tip":"Erenler (Sokak)"},{"id":702684,"il_id":33,"ilce_id":1892,"mahalle_id":31912,"ad":"Erenler Tepesi","tip":"Erenler Tepesi (Sokak)"},{"id":831842260,"il_id":33,"ilce_id":1892,"mahalle_id":31910,"ad":"Erenler/1","tip":"Erenler/1 (Sokak)"},{"id":357290,"il_id":33,"ilce_id":1892,"mahalle_id":31912,"ad":"Ergeni","tip":"Ergeni (Cadde)"},{"id":995842,"il_id":33,"ilce_id":1892,"mahalle_id":31911,"ad":"Eroğlu","tip":"Eroğlu (Sokak)"},{"id":939810,"il_id":33,"ilce_id":1892,"mahalle_id":182475,"ad":"Esenyurt","tip":"Esenyurt (Küme Evler)"},{"id":357565,"il_id":33,"ilce_id":1892,"mahalle_id":31910,"ad":"Eski Lise","tip":"Eski Lise (Cadde)"},{"id":360889870,"il_id":33,"ilce_id":1892,"mahalle_id":31910,"ad":"Eski Lise/1","tip":"Eski Lise/1 (Sokak)"},{"id":664706340,"il_id":33,"ilce_id":1892,"mahalle_id":31910,"ad":"Eski Lise/2","tip":"Eski Lise/2 (Sokak)"},{"id":473574,"il_id":33,"ilce_id":1892,"mahalle_id":31911,"ad":"Etebek","tip":"Etebek (Sokak)"},{"id":535425850,"il_id":33,"ilce_id":1892,"mahalle_id":31911,"ad":"Etebek/3","tip":"Etebek/3 (Sokak)"},{"id":887573070,"il_id":33,"ilce_id":1892,"mahalle_id":31911,"ad":"Etebekoluğu","tip":"Etebekoluğu (Sokak)"},{"id":358917,"il_id":33,"ilce_id":1892,"mahalle_id":31911,"ad":"Evcik Kayası","tip":"Evcik Kayası (Sokak)"},{"id":746547,"il_id":33,"ilce_id":1892,"mahalle_id":31911,"ad":"Evliya Çelebi","tip":"Evliya Çelebi (Sokak)"},{"id":249477070,"il_id":33,"ilce_id":1892,"mahalle_id":31911,"ad":"Eyyubi","tip":"Eyyubi (Cadde)"},{"id":472761,"il_id":33,"ilce_id":1892,"mahalle_id":31910,"ad":"Eğri","tip":"Eğri (Sokak)"},{"id":421439580,"il_id":33,"ilce_id":1892,"mahalle_id":31910,"ad":"Eğri/1","tip":"Eğri/1 (Sokak)"},{"id":467299,"il_id":33,"ilce_id":1892,"mahalle_id":31912,"ad":"Eğrice Oluk","tip":"Eğrice Oluk (Sokak)"},{"id":358074,"il_id":33,"ilce_id":1892,"mahalle_id":182459,"ad":"Eğriceviz","tip":"Eğriceviz (Küme Evler)"},{"id":816579,"il_id":33,"ilce_id":1892,"mahalle_id":182467,"ad":"Fakılar","tip":"Fakılar (Küme Evler)"},{"id":746548,"il_id":33,"ilce_id":1892,"mahalle_id":31911,"ad":"Farabi","tip":"Farabi (Sokak)"},{"id":357566,"il_id":33,"ilce_id":1892,"mahalle_id":31910,"ad":"Fatih","tip":"Fatih (Sokak)"},{"id":439859,"il_id":33,"ilce_id":1892,"mahalle_id":31911,"ad":"Fatih Sultan Mehmet","tip":"Fatih Sultan Mehmet (Cadde)"},{"id":332687980,"il_id":33,"ilce_id":1892,"mahalle_id":31911,"ad":"Fatih Sultan Mehmet/1","tip":"Fatih Sultan Mehmet/1 (Sokak)"},{"id":440248,"il_id":33,"ilce_id":1892,"mahalle_id":31911,"ad":"Fevzi Çakmak","tip":"Fevzi Çakmak (Sokak)"},{"id":363831640,"il_id":33,"ilce_id":1892,"mahalle_id":31911,"ad":"Fevzi Çakmak/1","tip":"Fevzi Çakmak/1 (Sokak)"},{"id":358918,"il_id":33,"ilce_id":1892,"mahalle_id":31911,"ad":"Fidan","tip":"Fidan (Sokak)"},{"id":358919,"il_id":33,"ilce_id":1892,"mahalle_id":31911,"ad":"Filamango","tip":"Filamango (Sokak)"},{"id":228774680,"il_id":33,"ilce_id":1892,"mahalle_id":31912,"ad":"Filamango","tip":"Filamango (Sokak)"},{"id":282200510,"il_id":33,"ilce_id":1892,"mahalle_id":31911,"ad":"Filamango/1","tip":"Filamango/1 (Sokak)"},{"id":473575,"il_id":33,"ilce_id":1892,"mahalle_id":31911,"ad":"Fındıklı","tip":"Fındıklı (Sokak)"},{"id":357567,"il_id":33,"ilce_id":1892,"mahalle_id":31910,"ad":"Fırın","tip":"Fırın (Sokak)"},{"id":357292,"il_id":33,"ilce_id":1892,"mahalle_id":31912,"ad":"Garipler","tip":"Garipler (Sokak)"},{"id":472762,"il_id":33,"ilce_id":1892,"mahalle_id":31910,"ad":"Gazi","tip":"Gazi (Sokak)"},{"id":685617,"il_id":33,"ilce_id":1892,"mahalle_id":31911,"ad":"Gazi Hüsnü Gökkaya","tip":"Gazi Hüsnü Gökkaya (Sokak)"},{"id":126342420,"il_id":33,"ilce_id":1892,"mahalle_id":31910,"ad":"Gazi/1","tip":"Gazi/1 (Sokak)"},{"id":746549,"il_id":33,"ilce_id":1892,"mahalle_id":31911,"ad":"Gazneliler","tip":"Gazneliler (Sokak)"},{"id":357568,"il_id":33,"ilce_id":1892,"mahalle_id":31910,"ad":"Göl","tip":"Göl (Sokak)"},{"id":335534700,"il_id":33,"ilce_id":1892,"mahalle_id":31910,"ad":"Göl/1","tip":"Göl/1 (Sokak)"},{"id":358920,"il_id":33,"ilce_id":1892,"mahalle_id":31911,"ad":"Göpter","tip":"Göpter (Cadde)"},{"id":445895470,"il_id":33,"ilce_id":1892,"mahalle_id":31911,"ad":"Göpter/1","tip":"Göpter/1 (Sokak)"},{"id":552144310,"il_id":33,"ilce_id":1892,"mahalle_id":31911,"ad":"Göpter/2","tip":"Göpter/2 (Sokak)"},{"id":504454,"il_id":33,"ilce_id":1892,"mahalle_id":182465,"ad":"Gücük","tip":"Gücük (Küme Evler)"},{"id":473576,"il_id":33,"ilce_id":1892,"mahalle_id":31911,"ad":"Gücükler","tip":"Gücükler (Sokak)"},{"id":358921,"il_id":33,"ilce_id":1892,"mahalle_id":31911,"ad":"Gül","tip":"Gül (Sokak)"},{"id":357569,"il_id":33,"ilce_id":1892,"mahalle_id":31910,"ad":"Gülhan","tip":"Gülhan (Sokak)"},{"id":358922,"il_id":33,"ilce_id":1892,"mahalle_id":31911,"ad":"Gülnar","tip":"Gülnar (Sokak)"},{"id":357293,"il_id":33,"ilce_id":1892,"mahalle_id":31912,"ad":"Güneşli","tip":"Güneşli (Sokak)"},{"id":329937,"il_id":33,"ilce_id":1892,"mahalle_id":182459,"ad":"Güreşler","tip":"Güreşler (Küme Evler)"},{"id":589670,"il_id":33,"ilce_id":1892,"mahalle_id":182459,"ad":"Güzle","tip":"Güzle (Cadde)"},{"id":271934,"il_id":33,"ilce_id":1892,"mahalle_id":182459,"ad":"Güzle (Taşlıekinlik)","tip":"Güzle (Taşlıekinlik) (Cadde)"},{"id":683604,"il_id":33,"ilce_id":1892,"mahalle_id":182459,"ad":"Hacı Yeri","tip":"Hacı Yeri (Küme Evler)"},{"id":357570,"il_id":33,"ilce_id":1892,"mahalle_id":31910,"ad":"Han","tip":"Han (Sokak)"},{"id":608808460,"il_id":33,"ilce_id":1892,"mahalle_id":31910,"ad":"Han/1","tip":"Han/1 (Sokak)"},{"id":472763,"il_id":33,"ilce_id":1892,"mahalle_id":31910,"ad":"Hapkapan","tip":"Hapkapan (Sokak)"},{"id":551214790,"il_id":33,"ilce_id":1892,"mahalle_id":31910,"ad":"Hapkapan/1","tip":"Hapkapan/1 (Sokak)"},{"id":357294,"il_id":33,"ilce_id":1892,"mahalle_id":31912,"ad":"Harap","tip":"Harap (Sokak)"},{"id":357615,"il_id":33,"ilce_id":1892,"mahalle_id":31910,"ad":"Havare","tip":"Havare (Sokak)"},{"id":746550,"il_id":33,"ilce_id":1892,"mahalle_id":31911,"ad":"Hazar","tip":"Hazar (Sokak)"},{"id":507217,"il_id":33,"ilce_id":1892,"mahalle_id":182467,"ad":"Haçgediği","tip":"Haçgediği (Küme Evler)"},{"id":357571,"il_id":33,"ilce_id":1892,"mahalle_id":31910,"ad":"Hekim Oğlu","tip":"Hekim Oğlu (Sokak)"},{"id":357572,"il_id":33,"ilce_id":1892,"mahalle_id":31910,"ad":"Herekli","tip":"Herekli (Sokak)"},{"id":357295,"il_id":33,"ilce_id":1892,"mahalle_id":31912,"ad":"Hilal","tip":"Hilal (Sokak)"},{"id":467300,"il_id":33,"ilce_id":1892,"mahalle_id":31912,"ad":"Hızar","tip":"Hızar (Sokak)"},{"id":357583,"il_id":33,"ilce_id":1892,"mahalle_id":31910,"ad":"Ikiz","tip":"Ikiz (Sokak)"},{"id":568059550,"il_id":33,"ilce_id":1892,"mahalle_id":31910,"ad":"Ikiz/1","tip":"Ikiz/1 (Sokak)"},{"id":374459880,"il_id":33,"ilce_id":1892,"mahalle_id":31910,"ad":"Ikiz/2","tip":"Ikiz/2 (Sokak)"},{"id":357584,"il_id":33,"ilce_id":1892,"mahalle_id":31910,"ad":"Inci","tip":"Inci (Sokak)"},{"id":890916,"il_id":33,"ilce_id":1892,"mahalle_id":31911,"ad":"Ismail Tepebağlı","tip":"Ismail Tepebağlı (Sokak)"},{"id":357542,"il_id":33,"ilce_id":1892,"mahalle_id":31910,"ad":"Istemihan Talay","tip":"Istemihan Talay (Cadde)"},{"id":251454830,"il_id":33,"ilce_id":1892,"mahalle_id":31910,"ad":"Istemihan Talay/1","tip":"Istemihan Talay/1 (Sokak)"},{"id":682162,"il_id":33,"ilce_id":1892,"mahalle_id":31911,"ad":"Istiklal","tip":"Istiklal (Sokak)"},{"id":357543,"il_id":33,"ilce_id":1892,"mahalle_id":31910,"ad":"Izmir","tip":"Izmir (Sokak)"},{"id":636652770,"il_id":33,"ilce_id":1892,"mahalle_id":31910,"ad":"Izmir/1","tip":"Izmir/1 (Sokak)"},{"id":472764,"il_id":33,"ilce_id":1892,"mahalle_id":31910,"ad":"Kalaycı","tip":"Kalaycı (Sokak)"},{"id":473577,"il_id":33,"ilce_id":1892,"mahalle_id":31911,"ad":"Kaleardı","tip":"Kaleardı (Cadde)"},{"id":235607410,"il_id":33,"ilce_id":1892,"mahalle_id":31911,"ad":"Kaleardı/1","tip":"Kaleardı/1 (Sokak)"},{"id":494022330,"il_id":33,"ilce_id":1892,"mahalle_id":31911,"ad":"Kaleardı/2","tip":"Kaleardı/2 (Sokak)"},{"id":357573,"il_id":33,"ilce_id":1892,"mahalle_id":31910,"ad":"Kaleönü","tip":"Kaleönü (Cadde)"},{"id":158378000,"il_id":33,"ilce_id":1892,"mahalle_id":31910,"ad":"Kaleönü/1","tip":"Kaleönü/1 (Sokak)"},{"id":358923,"il_id":33,"ilce_id":1892,"mahalle_id":31911,"ad":"Kamp","tip":"Kamp (Sokak)"},{"id":357574,"il_id":33,"ilce_id":1892,"mahalle_id":31910,"ad":"Kamışlı","tip":"Kamışlı (Sokak)"},{"id":357575,"il_id":33,"ilce_id":1892,"mahalle_id":31910,"ad":"Kanarya","tip":"Kanarya (Sokak)"},{"id":472765,"il_id":33,"ilce_id":1892,"mahalle_id":31910,"ad":"Kanuni","tip":"Kanuni (Sokak)"},{"id":885101360,"il_id":33,"ilce_id":1892,"mahalle_id":31910,"ad":"Kanuni/1","tip":"Kanuni/1 (Sokak)"},{"id":674856,"il_id":33,"ilce_id":1892,"mahalle_id":182459,"ad":"Kara Hasan Cayırlığı","tip":"Kara Hasan Cayırlığı (Küme Evler)"},{"id":743014,"il_id":33,"ilce_id":1892,"mahalle_id":31911,"ad":"Karacaoğlan","tip":"Karacaoğlan (Sokak)"},{"id":440243,"il_id":33,"ilce_id":1892,"mahalle_id":31911,"ad":"Karadeniz","tip":"Karadeniz (Cadde)"},{"id":746551,"il_id":33,"ilce_id":1892,"mahalle_id":31911,"ad":"Karahanlılar","tip":"Karahanlılar (Sokak)"},{"id":372050,"il_id":33,"ilce_id":1892,"mahalle_id":31911,"ad":"Karanfil","tip":"Karanfil (Sokak)"},{"id":375623450,"il_id":33,"ilce_id":1892,"mahalle_id":31911,"ad":"Karanfil/1","tip":"Karanfil/1 (Sokak)"},{"id":358924,"il_id":33,"ilce_id":1892,"mahalle_id":31911,"ad":"Kargılı","tip":"Kargılı (Sokak)"},{"id":511419,"il_id":33,"ilce_id":1892,"mahalle_id":182467,"ad":"Karova","tip":"Karova (Küme Evler)"},{"id":357296,"il_id":33,"ilce_id":1892,"mahalle_id":31912,"ad":"Kasap","tip":"Kasap (Sokak)"},{"id":357576,"il_id":33,"ilce_id":1892,"mahalle_id":31910,"ad":"Katranlı","tip":"Katranlı (Sokak)"},{"id":510100310,"il_id":33,"ilce_id":1892,"mahalle_id":31910,"ad":"Katranlı/1","tip":"Katranlı/1 (Sokak)"},{"id":144551330,"il_id":33,"ilce_id":1892,"mahalle_id":31910,"ad":"Katranlı/2","tip":"Katranlı/2 (Sokak)"},{"id":265347190,"il_id":33,"ilce_id":1892,"mahalle_id":31910,"ad":"Katranlı/3","tip":"Katranlı/3 (Sokak)"},{"id":376294900,"il_id":33,"ilce_id":1892,"mahalle_id":31910,"ad":"Katranlı/4","tip":"Katranlı/4 (Sokak)"},{"id":433608170,"il_id":33,"ilce_id":1892,"mahalle_id":31910,"ad":"Katranlı/5","tip":"Katranlı/5 (Sokak)"},{"id":189587020,"il_id":33,"ilce_id":1892,"mahalle_id":31910,"ad":"Katranlı/6","tip":"Katranlı/6 (Sokak)"},{"id":357577,"il_id":33,"ilce_id":1892,"mahalle_id":31910,"ad":"Kavaklı","tip":"Kavaklı (Sokak)"},{"id":722738990,"il_id":33,"ilce_id":1892,"mahalle_id":31910,"ad":"Kavaklı/1","tip":"Kavaklı/1 (Sokak)"},{"id":467301,"il_id":33,"ilce_id":1892,"mahalle_id":31912,"ad":"Kaya","tip":"Kaya (Sokak)"},{"id":358925,"il_id":33,"ilce_id":1892,"mahalle_id":31911,"ad":"Kayseri","tip":"Kayseri (Sokak)"},{"id":489533350,"il_id":33,"ilce_id":1892,"mahalle_id":31911,"ad":"Kayseri/1","tip":"Kayseri/1 (Sokak)"},{"id":743015,"il_id":33,"ilce_id":1892,"mahalle_id":31911,"ad":"Kazım Karabekir","tip":"Kazım Karabekir (Sokak)"},{"id":472766,"il_id":33,"ilce_id":1892,"mahalle_id":31910,"ad":"Kebap Oluğu","tip":"Kebap Oluğu (Sokak)"},{"id":357297,"il_id":33,"ilce_id":1892,"mahalle_id":31912,"ad":"Keloluk","tip":"Keloluk (Sokak)"},{"id":357298,"il_id":33,"ilce_id":1892,"mahalle_id":31912,"ad":"Kemal Eroğlu","tip":"Kemal Eroğlu (Sokak)"},{"id":467302,"il_id":33,"ilce_id":1892,"mahalle_id":31912,"ad":"Kemal Çatak","tip":"Kemal Çatak (Sokak)"},{"id":357299,"il_id":33,"ilce_id":1892,"mahalle_id":31912,"ad":"Kepir","tip":"Kepir (Sokak)"},{"id":357587,"il_id":33,"ilce_id":1892,"mahalle_id":31910,"ad":"Kirazlı","tip":"Kirazlı (Sokak)"},{"id":827717420,"il_id":33,"ilce_id":1892,"mahalle_id":31910,"ad":"Kirazlı/1","tip":"Kirazlı/1 (Sokak)"},{"id":357303,"il_id":33,"ilce_id":1892,"mahalle_id":31912,"ad":"Kireç Ocağı","tip":"Kireç Ocağı (Sokak)"},{"id":743017,"il_id":33,"ilce_id":1892,"mahalle_id":31911,"ad":"Koca Yusuf","tip":"Koca Yusuf (Sokak)"},{"id":119989290,"il_id":33,"ilce_id":1892,"mahalle_id":31911,"ad":"Koca Yusuf/1","tip":"Koca Yusuf/1 (Sokak)"},{"id":357585,"il_id":33,"ilce_id":1892,"mahalle_id":31910,"ad":"Kocaoluk/cumayakası","tip":"Kocaoluk/cumayakası (Sokak)"},{"id":511957,"il_id":33,"ilce_id":1892,"mahalle_id":182467,"ad":"Kocaoluk/fakılar","tip":"Kocaoluk/fakılar (Küme Evler)"},{"id":357300,"il_id":33,"ilce_id":1892,"mahalle_id":31912,"ad":"Kozağacı","tip":"Kozağacı (Sokak)"},{"id":326261030,"il_id":33,"ilce_id":1892,"mahalle_id":31912,"ad":"Kozağacı/1","tip":"Kozağacı/1 (Sokak)"},{"id":291110930,"il_id":33,"ilce_id":1892,"mahalle_id":31912,"ad":"Kozağaç/1","tip":"Kozağaç/1 (Sokak)"},{"id":476647,"il_id":33,"ilce_id":1892,"mahalle_id":31911,"ad":"Kurs","tip":"Kurs (Sokak)"},{"id":357301,"il_id":33,"ilce_id":1892,"mahalle_id":31912,"ad":"Kuyu","tip":"Kuyu (Sokak)"},{"id":485709,"il_id":33,"ilce_id":1892,"mahalle_id":182471,"ad":"Körmenlik","tip":"Körmenlik (Küme Evler)"},{"id":357586,"il_id":33,"ilce_id":1892,"mahalle_id":31910,"ad":"Köroğlu","tip":"Köroğlu (Sokak)"},{"id":358926,"il_id":33,"ilce_id":1892,"mahalle_id":31911,"ad":"Körükler","tip":"Körükler (Sokak)"},{"id":467303,"il_id":33,"ilce_id":1892,"mahalle_id":31912,"ad":"Köy Içi","tip":"Köy Içi (Sokak)"},{"id":372051,"il_id":33,"ilce_id":1892,"mahalle_id":31911,"ad":"Köşker","tip":"Köşker (Sokak)"},{"id":289885410,"il_id":33,"ilce_id":1892,"mahalle_id":31911,"ad":"Köşker/3","tip":"Köşker/3 (Sokak)"},{"id":352476,"il_id":33,"ilce_id":1892,"mahalle_id":31911,"ad":"Künk","tip":"Künk (Sokak)"},{"id":476648,"il_id":33,"ilce_id":1892,"mahalle_id":31911,"ad":"Küpeli","tip":"Küpeli (Sokak)"},{"id":152027730,"il_id":33,"ilce_id":1892,"mahalle_id":31911,"ad":"Küpeli/1","tip":"Küpeli/1 (Sokak)"},{"id":472770,"il_id":33,"ilce_id":1892,"mahalle_id":31910,"ad":"Küçük","tip":"Küçük (Sokak)"},{"id":357302,"il_id":33,"ilce_id":1892,"mahalle_id":31912,"ad":"Küçük Kale","tip":"Küçük Kale (Sokak)"},{"id":343967701,"il_id":33,"ilce_id":1892,"mahalle_id":31911,"ad":"Küçük Kale","tip":"Küçük Kale (Sokak)"},{"id":743016,"il_id":33,"ilce_id":1892,"mahalle_id":31911,"ad":"Kırım","tip":"Kırım (Sokak)"},{"id":472769,"il_id":33,"ilce_id":1892,"mahalle_id":31910,"ad":"Kısa","tip":"Kısa (Sokak)"},{"id":485267,"il_id":33,"ilce_id":1892,"mahalle_id":182473,"ad":"Kısıkdere","tip":"Kısıkdere (Küme Evler)"},{"id":504413,"il_id":33,"ilce_id":1892,"mahalle_id":182465,"ad":"Kıyrak Beleni","tip":"Kıyrak Beleni (Küme Evler)"},{"id":832928,"il_id":33,"ilce_id":1892,"mahalle_id":31910,"ad":"Kızıloluk","tip":"Kızıloluk (Sokak)"},{"id":352477,"il_id":33,"ilce_id":1892,"mahalle_id":31911,"ad":"Lale","tip":"Lale (Sokak)"},{"id":655257270,"il_id":33,"ilce_id":1892,"mahalle_id":31911,"ad":"Lale/1","tip":"Lale/1 (Sokak)"},{"id":357588,"il_id":33,"ilce_id":1892,"mahalle_id":31910,"ad":"Levent","tip":"Levent (Sokak)"},{"id":469763,"il_id":33,"ilce_id":1892,"mahalle_id":31911,"ad":"Leylak","tip":"Leylak (Sokak)"},{"id":357589,"il_id":33,"ilce_id":1892,"mahalle_id":31910,"ad":"Limonlu","tip":"Limonlu (Sokak)"},{"id":377323690,"il_id":33,"ilce_id":1892,"mahalle_id":31910,"ad":"Limonlu/1","tip":"Limonlu/1 (Sokak)"},{"id":374680970,"il_id":33,"ilce_id":1892,"mahalle_id":31910,"ad":"Limonlu/2","tip":"Limonlu/2 (Sokak)"},{"id":357304,"il_id":33,"ilce_id":1892,"mahalle_id":31912,"ad":"Lojman","tip":"Lojman (Sokak)"},{"id":205088340,"il_id":33,"ilce_id":1892,"mahalle_id":31912,"ad":"Lojman/1","tip":"Lojman/1 (Sokak)"},{"id":343392420,"il_id":33,"ilce_id":1892,"mahalle_id":31912,"ad":"Lojman/2","tip":"Lojman/2 (Sokak)"},{"id":746552,"il_id":33,"ilce_id":1892,"mahalle_id":31911,"ad":"Lokman Hekim","tip":"Lokman Hekim (Sokak)"},{"id":472771,"il_id":33,"ilce_id":1892,"mahalle_id":31910,"ad":"Maden","tip":"Maden (Sokak)"},{"id":749793370,"il_id":33,"ilce_id":1892,"mahalle_id":31910,"ad":"Maden/1","tip":"Maden/1 (Sokak)"},{"id":746553,"il_id":33,"ilce_id":1892,"mahalle_id":31911,"ad":"Mahzuni şErif","tip":"Mahzuni şErif (Sokak)"},{"id":746554,"il_id":33,"ilce_id":1892,"mahalle_id":31911,"ad":"Malazgirt","tip":"Malazgirt (Sokak)"},{"id":275210,"il_id":33,"ilce_id":1892,"mahalle_id":31911,"ad":"Marmara","tip":"Marmara (Cadde)"},{"id":352478,"il_id":33,"ilce_id":1892,"mahalle_id":31911,"ad":"Medine Kuyusu","tip":"Medine Kuyusu (Sokak)"},{"id":275211,"il_id":33,"ilce_id":1892,"mahalle_id":31911,"ad":"Mehmet Akif Ersoy","tip":"Mehmet Akif Ersoy (Cadde)"},{"id":890918,"il_id":33,"ilce_id":1892,"mahalle_id":31911,"ad":"Mehmet Akın","tip":"Mehmet Akın (Sokak)"},{"id":219469750,"il_id":33,"ilce_id":1892,"mahalle_id":31911,"ad":"Mehmet Akın/1","tip":"Mehmet Akın/1 (Sokak)"},{"id":357305,"il_id":33,"ilce_id":1892,"mahalle_id":31912,"ad":"Mehmet Kur","tip":"Mehmet Kur (Sokak)"},{"id":352479,"il_id":33,"ilce_id":1892,"mahalle_id":31911,"ad":"Mehmetçik","tip":"Mehmetçik (Sokak)"},{"id":476649,"il_id":33,"ilce_id":1892,"mahalle_id":31911,"ad":"Menekşe","tip":"Menekşe (Sokak)"},{"id":407585670,"il_id":33,"ilce_id":1892,"mahalle_id":31911,"ad":"Menekşe/1","tip":"Menekşe/1 (Sokak)"},{"id":357590,"il_id":33,"ilce_id":1892,"mahalle_id":31910,"ad":"Mercan","tip":"Mercan (Sokak)"},{"id":467304,"il_id":33,"ilce_id":1892,"mahalle_id":31912,"ad":"Mercimek","tip":"Mercimek (Sokak)"},{"id":357306,"il_id":33,"ilce_id":1892,"mahalle_id":31912,"ad":"Merdivenli","tip":"Merdivenli (Sokak)"},{"id":344377560,"il_id":33,"ilce_id":1892,"mahalle_id":31912,"ad":"Merdivenli/1","tip":"Merdivenli/1 (Sokak)"},{"id":508333,"il_id":33,"ilce_id":1892,"mahalle_id":182463,"ad":"Merkez/belçınar","tip":"Merkez/belçınar (Küme Evler)"},{"id":510619,"il_id":33,"ilce_id":1892,"mahalle_id":182465,"ad":"Merkez/darıpınarı","tip":"Merkez/darıpınarı (Küme Evler)"},{"id":500359,"il_id":33,"ilce_id":1892,"mahalle_id":182469,"ad":"Merkez/giden","tip":"Merkez/giden (Küme Evler)"},{"id":484449,"il_id":33,"ilce_id":1892,"mahalle_id":182473,"ad":"Merkez/kesecik","tip":"Merkez/kesecik (Küme Evler)"},{"id":500586,"il_id":33,"ilce_id":1892,"mahalle_id":182475,"ad":"Merkez/korucak","tip":"Merkez/korucak (Küme Evler)"},{"id":493860,"il_id":33,"ilce_id":1892,"mahalle_id":182477,"ad":"Merkez/sarıkavak","tip":"Merkez/sarıkavak (Küme Evler)"},{"id":467305,"il_id":33,"ilce_id":1892,"mahalle_id":31912,"ad":"Mersin","tip":"Mersin (Sokak)"},{"id":746555,"il_id":33,"ilce_id":1892,"mahalle_id":31911,"ad":"Mevlana","tip":"Mevlana (Cadde)"},{"id":746556,"il_id":33,"ilce_id":1892,"mahalle_id":31911,"ad":"Mimar Sinan","tip":"Mimar Sinan (Sokak)"},{"id":111406050,"il_id":33,"ilce_id":1892,"mahalle_id":31910,"ad":"Mirici","tip":"Mirici (Sokak)"},{"id":890919,"il_id":33,"ilce_id":1892,"mahalle_id":31911,"ad":"Mustafa Ahmet Çatak","tip":"Mustafa Ahmet Çatak (Sokak)"},{"id":890914,"il_id":33,"ilce_id":1892,"mahalle_id":31911,"ad":"Namık Kemal","tip":"Namık Kemal (Sokak)"},{"id":357307,"il_id":33,"ilce_id":1892,"mahalle_id":31912,"ad":"Narin","tip":"Narin (Sokak)"},{"id":522886850,"il_id":33,"ilce_id":1892,"mahalle_id":31912,"ad":"Narin/1","tip":"Narin/1 (Sokak)"},{"id":746557,"il_id":33,"ilce_id":1892,"mahalle_id":31911,"ad":"Nasreddin Hoca","tip":"Nasreddin Hoca (Sokak)"},{"id":275197,"il_id":33,"ilce_id":1892,"mahalle_id":31911,"ad":"Nene Hatun","tip":"Nene Hatun (Sokak)"},{"id":432345900,"il_id":33,"ilce_id":1892,"mahalle_id":31911,"ad":"Nene Hatun/1","tip":"Nene Hatun/1 (Sokak)"},{"id":352480,"il_id":33,"ilce_id":1892,"mahalle_id":31911,"ad":"Nergiz","tip":"Nergiz (Sokak)"},{"id":372052,"il_id":33,"ilce_id":1892,"mahalle_id":31911,"ad":"Niğde","tip":"Niğde (Sokak)"},{"id":472772,"il_id":33,"ilce_id":1892,"mahalle_id":31910,"ad":"Ocak","tip":"Ocak (Sokak)"},{"id":583172150,"il_id":33,"ilce_id":1892,"mahalle_id":31910,"ad":"Ocak/1","tip":"Ocak/1 (Sokak)"},{"id":294900340,"il_id":33,"ilce_id":1892,"mahalle_id":31910,"ad":"Ocak/2","tip":"Ocak/2 (Sokak)"},{"id":357592,"il_id":33,"ilce_id":1892,"mahalle_id":31910,"ad":"Okul","tip":"Okul (Sokak)"},{"id":357308,"il_id":33,"ilce_id":1892,"mahalle_id":31912,"ad":"Orman","tip":"Orman (Sokak)"},{"id":357593,"il_id":33,"ilce_id":1892,"mahalle_id":31910,"ad":"Orta","tip":"Orta (Sokak)"},{"id":686312,"il_id":33,"ilce_id":1892,"mahalle_id":31911,"ad":"Oruç Reis","tip":"Oruç Reis (Sokak)"},{"id":105719820,"il_id":33,"ilce_id":1892,"mahalle_id":31911,"ad":"Oruç Reis/1","tip":"Oruç Reis/1 (Sokak)"},{"id":352481,"il_id":33,"ilce_id":1892,"mahalle_id":31911,"ad":"Otel","tip":"Otel (Sokak)"},{"id":472773,"il_id":33,"ilce_id":1892,"mahalle_id":31910,"ad":"Palmiye","tip":"Palmiye (Sokak)"},{"id":467315,"il_id":33,"ilce_id":1892,"mahalle_id":182459,"ad":"Pamukluk","tip":"Pamukluk (Küme Evler)"},{"id":476650,"il_id":33,"ilce_id":1892,"mahalle_id":31911,"ad":"Papatya","tip":"Papatya (Sokak)"},{"id":926074560,"il_id":33,"ilce_id":1892,"mahalle_id":31911,"ad":"Papatya/1","tip":"Papatya/1 (Sokak)"},{"id":357309,"il_id":33,"ilce_id":1892,"mahalle_id":31912,"ad":"Pazar","tip":"Pazar (Sokak)"},{"id":495206200,"il_id":33,"ilce_id":1892,"mahalle_id":31910,"ad":"Pazar","tip":"Pazar (Sokak)"},{"id":352482,"il_id":33,"ilce_id":1892,"mahalle_id":31911,"ad":"Paşa","tip":"Paşa (Sokak)"},{"id":528668030,"il_id":33,"ilce_id":1892,"mahalle_id":31911,"ad":"Paşa/1","tip":"Paşa/1 (Sokak)"},{"id":491192740,"il_id":33,"ilce_id":1892,"mahalle_id":31911,"ad":"Paşa/2","tip":"Paşa/2 (Sokak)"},{"id":357591,"il_id":33,"ilce_id":1892,"mahalle_id":31910,"ad":"Paşalar","tip":"Paşalar (Sokak)"},{"id":357594,"il_id":33,"ilce_id":1892,"mahalle_id":31910,"ad":"Pelitli","tip":"Pelitli (Sokak)"},{"id":743018,"il_id":33,"ilce_id":1892,"mahalle_id":31911,"ad":"Pir Sultan Abdal","tip":"Pir Sultan Abdal (Sokak)"},{"id":357596,"il_id":33,"ilce_id":1892,"mahalle_id":31910,"ad":"Posta","tip":"Posta (Sokak)"},{"id":467306,"il_id":33,"ilce_id":1892,"mahalle_id":31912,"ad":"Poyraz","tip":"Poyraz (Sokak)"},{"id":357595,"il_id":33,"ilce_id":1892,"mahalle_id":31910,"ad":"Pınar","tip":"Pınar (Sokak)"},{"id":357310,"il_id":33,"ilce_id":1892,"mahalle_id":31912,"ad":"Sabri Etral","tip":"Sabri Etral (Sokak)"},{"id":472774,"il_id":33,"ilce_id":1892,"mahalle_id":31910,"ad":"Sakarya","tip":"Sakarya (Sokak)"},{"id":890923,"il_id":33,"ilce_id":1892,"mahalle_id":31910,"ad":"Salah Gökmen","tip":"Salah Gökmen (Sokak)"},{"id":357597,"il_id":33,"ilce_id":1892,"mahalle_id":31910,"ad":"Sarmaşık","tip":"Sarmaşık (Sokak)"},{"id":357311,"il_id":33,"ilce_id":1892,"mahalle_id":31912,"ad":"Sarp","tip":"Sarp (Sokak)"},{"id":743022,"il_id":33,"ilce_id":1892,"mahalle_id":31911,"ad":"Saruhan","tip":"Saruhan (Sokak)"},{"id":503124,"il_id":33,"ilce_id":1892,"mahalle_id":182467,"ad":"Sarıkaya","tip":"Sarıkaya (Küme Evler)"},{"id":502067,"il_id":33,"ilce_id":1892,"mahalle_id":182467,"ad":"Sarıkaya Dibi","tip":"Sarıkaya Dibi (Küme Evler)"},{"id":490094,"il_id":33,"ilce_id":1892,"mahalle_id":182479,"ad":"Sarıkoyak","tip":"Sarıkoyak (Küme Evler)"},{"id":357598,"il_id":33,"ilce_id":1892,"mahalle_id":31910,"ad":"Sayalı","tip":"Sayalı (Sokak)"},{"id":467307,"il_id":33,"ilce_id":1892,"mahalle_id":31912,"ad":"Saybaşı","tip":"Saybaşı (Sokak)"},{"id":176636670,"il_id":33,"ilce_id":1892,"mahalle_id":31912,"ad":"Saybaşı/1","tip":"Saybaşı/1 (Sokak)"},{"id":472775,"il_id":33,"ilce_id":1892,"mahalle_id":31910,"ad":"Sağlık","tip":"Sağlık (Sokak)"},{"id":925948030,"il_id":33,"ilce_id":1892,"mahalle_id":31910,"ad":"Sağlık/1","tip":"Sağlık/1 (Sokak)"},{"id":357599,"il_id":33,"ilce_id":1892,"mahalle_id":31910,"ad":"Sebil","tip":"Sebil (Sokak)"},{"id":153450100,"il_id":33,"ilce_id":1892,"mahalle_id":182459,"ad":"Sebil 1","tip":"Sebil 1 (Sokak)"},{"id":204752810,"il_id":33,"ilce_id":1892,"mahalle_id":182459,"ad":"Sebil 2","tip":"Sebil 2 (Sokak)"},{"id":462684880,"il_id":33,"ilce_id":1892,"mahalle_id":182459,"ad":"Sebil 3","tip":"Sebil 3 (Sokak)"},{"id":316985170,"il_id":33,"ilce_id":1892,"mahalle_id":31910,"ad":"Sebil/1","tip":"Sebil/1 (Sokak)"},{"id":318460740,"il_id":33,"ilce_id":1892,"mahalle_id":31910,"ad":"Sebil/3","tip":"Sebil/3 (Sokak)"},{"id":930288760,"il_id":33,"ilce_id":1892,"mahalle_id":31910,"ad":"Sebil/4","tip":"Sebil/4 (Sokak)"},{"id":357312,"il_id":33,"ilce_id":1892,"mahalle_id":31912,"ad":"Seda","tip":"Seda (Sokak)"},{"id":255762810,"il_id":33,"ilce_id":1892,"mahalle_id":31912,"ad":"Seda/1","tip":"Seda/1 (Sokak)"},{"id":674467730,"il_id":33,"ilce_id":1892,"mahalle_id":31912,"ad":"Seda/2","tip":"Seda/2 (Sokak)"},{"id":357313,"il_id":33,"ilce_id":1892,"mahalle_id":31912,"ad":"Sekili","tip":"Sekili (Sokak)"},{"id":372053,"il_id":33,"ilce_id":1892,"mahalle_id":31911,"ad":"Selvi","tip":"Selvi (Sokak)"},{"id":357314,"il_id":33,"ilce_id":1892,"mahalle_id":31912,"ad":"Serap","tip":"Serap (Sokak)"},{"id":275192,"il_id":33,"ilce_id":1892,"mahalle_id":31911,"ad":"Serin","tip":"Serin (Sokak)"},{"id":945474,"il_id":33,"ilce_id":1892,"mahalle_id":31910,"ad":"Sezer","tip":"Sezer (Sokak)"},{"id":357602,"il_id":33,"ilce_id":1892,"mahalle_id":31910,"ad":"Silifke","tip":"Silifke (Sokak)"},{"id":352483,"il_id":33,"ilce_id":1892,"mahalle_id":31911,"ad":"Sinap","tip":"Sinap (Sokak)"},{"id":614235620,"il_id":33,"ilce_id":1892,"mahalle_id":31911,"ad":"Sinap/1","tip":"Sinap/1 (Sokak)"},{"id":357600,"il_id":33,"ilce_id":1892,"mahalle_id":31910,"ad":"Stad","tip":"Stad (Sokak)"},{"id":664652460,"il_id":33,"ilce_id":1892,"mahalle_id":31910,"ad":"Stad/1","tip":"Stad/1 (Sokak)"},{"id":500762,"il_id":33,"ilce_id":1892,"mahalle_id":182467,"ad":"Su Uçtu","tip":"Su Uçtu (Küme Evler)"},{"id":357601,"il_id":33,"ilce_id":1892,"mahalle_id":31910,"ad":"Sümbül","tip":"Sümbül (Sokak)"},{"id":641577790,"il_id":33,"ilce_id":1892,"mahalle_id":31910,"ad":"Sümbül/2","tip":"Sümbül/2 (Sokak)"},{"id":472776,"il_id":33,"ilce_id":1892,"mahalle_id":31910,"ad":"Sürmeli","tip":"Sürmeli (Sokak)"},{"id":133872790,"il_id":33,"ilce_id":1892,"mahalle_id":31910,"ad":"Sürmeli/1","tip":"Sürmeli/1 (Sokak)"},{"id":510540,"il_id":33,"ilce_id":1892,"mahalle_id":182463,"ad":"Sütlüce","tip":"Sütlüce (Küme Evler)"},{"id":467308,"il_id":33,"ilce_id":1892,"mahalle_id":31912,"ad":"Tahtalı Köprü","tip":"Tahtalı Köprü (Sokak)"},{"id":782144260,"il_id":33,"ilce_id":1892,"mahalle_id":31912,"ad":"Tahtalı Köprü/1","tip":"Tahtalı Köprü/1 (Sokak)"},{"id":357603,"il_id":33,"ilce_id":1892,"mahalle_id":31910,"ad":"Talıç","tip":"Talıç (Cadde)"},{"id":472777,"il_id":33,"ilce_id":1892,"mahalle_id":31910,"ad":"Tarla","tip":"Tarla (Sokak)"},{"id":357315,"il_id":33,"ilce_id":1892,"mahalle_id":31912,"ad":"Tarsus","tip":"Tarsus (Cadde)"},{"id":357604,"il_id":33,"ilce_id":1892,"mahalle_id":31910,"ad":"Tarsus","tip":"Tarsus (Cadde)"},{"id":357252,"il_id":33,"ilce_id":1892,"mahalle_id":31911,"ad":"Tarım","tip":"Tarım (Sokak)"},{"id":534343870,"il_id":33,"ilce_id":1892,"mahalle_id":31911,"ad":"Tarım/10","tip":"Tarım/10 (Sokak)"},{"id":168235690,"il_id":33,"ilce_id":1892,"mahalle_id":31911,"ad":"Tarım/2","tip":"Tarım/2 (Sokak)"},{"id":410924870,"il_id":33,"ilce_id":1892,"mahalle_id":31911,"ad":"Tarım/5","tip":"Tarım/5 (Sokak)"},{"id":126943520,"il_id":33,"ilce_id":1892,"mahalle_id":31911,"ad":"Tarım/7","tip":"Tarım/7 (Sokak)"},{"id":727433960,"il_id":33,"ilce_id":1892,"mahalle_id":31911,"ad":"Tarım/8","tip":"Tarım/8 (Sokak)"},{"id":357316,"il_id":33,"ilce_id":1892,"mahalle_id":31912,"ad":"Taşlı","tip":"Taşlı (Sokak)"},{"id":357253,"il_id":33,"ilce_id":1892,"mahalle_id":31911,"ad":"Taşucu","tip":"Taşucu (Sokak)"},{"id":357317,"il_id":33,"ilce_id":1892,"mahalle_id":31912,"ad":"Telli","tip":"Telli (Sokak)"},{"id":357254,"il_id":33,"ilce_id":1892,"mahalle_id":31911,"ad":"Tepe","tip":"Tepe (Sokak)"},{"id":343704290,"il_id":33,"ilce_id":1892,"mahalle_id":31911,"ad":"Tepe/1","tip":"Tepe/1 (Sokak)"},{"id":357255,"il_id":33,"ilce_id":1892,"mahalle_id":31911,"ad":"Tepebağ","tip":"Tepebağ (Sokak)"},{"id":346423710,"il_id":33,"ilce_id":1892,"mahalle_id":31911,"ad":"Tepebağ/1","tip":"Tepebağ/1 (Sokak)"},{"id":709378,"il_id":33,"ilce_id":1892,"mahalle_id":31912,"ad":"Tepecik","tip":"Tepecik (Sokak)"},{"id":467309,"il_id":33,"ilce_id":1892,"mahalle_id":31912,"ad":"Tepensesi","tip":"Tepensesi (Cadde)"},{"id":191800091,"il_id":33,"ilce_id":1892,"mahalle_id":31910,"ad":"Tepensesi","tip":"Tepensesi (Cadde)"},{"id":555718480,"il_id":33,"ilce_id":1892,"mahalle_id":31912,"ad":"Tepensesi/1","tip":"Tepensesi/1 (Sokak)"},{"id":506675830,"il_id":33,"ilce_id":1892,"mahalle_id":31912,"ad":"Tepensesi1","tip":"Tepensesi1 (Sokak)"},{"id":357256,"il_id":33,"ilce_id":1892,"mahalle_id":31911,"ad":"Tomurcuk","tip":"Tomurcuk (Sokak)"},{"id":357605,"il_id":33,"ilce_id":1892,"mahalle_id":31910,"ad":"Topak Oluk","tip":"Topak Oluk (Sokak)"},{"id":130738120,"il_id":33,"ilce_id":1892,"mahalle_id":31910,"ad":"Topak Oluk/1","tip":"Topak Oluk/1 (Sokak)"},{"id":777452480,"il_id":33,"ilce_id":1892,"mahalle_id":31910,"ad":"Topak Oluk/2","tip":"Topak Oluk/2 (Sokak)"},{"id":472778,"il_id":33,"ilce_id":1892,"mahalle_id":31910,"ad":"Topaklı","tip":"Topaklı (Sokak)"},{"id":291406470,"il_id":33,"ilce_id":1892,"mahalle_id":31910,"ad":"Topaklı/3","tip":"Topaklı/3 (Sokak)"},{"id":484925,"il_id":33,"ilce_id":1892,"mahalle_id":182473,"ad":"Topaktaş","tip":"Topaktaş (Küme Evler)"},{"id":357257,"il_id":33,"ilce_id":1892,"mahalle_id":31911,"ad":"Toraççık","tip":"Toraççık (Sokak)"},{"id":357258,"il_id":33,"ilce_id":1892,"mahalle_id":31911,"ad":"Toros","tip":"Toros (Cadde)"},{"id":600366620,"il_id":33,"ilce_id":1892,"mahalle_id":31911,"ad":"Toros/2","tip":"Toros/2 (Sokak)"},{"id":357259,"il_id":33,"ilce_id":1892,"mahalle_id":31911,"ad":"Torul","tip":"Torul (Sokak)"},{"id":357260,"il_id":33,"ilce_id":1892,"mahalle_id":31911,"ad":"Tulumba","tip":"Tulumba (Sokak)"},{"id":746558,"il_id":33,"ilce_id":1892,"mahalle_id":31911,"ad":"Turgut Reis","tip":"Turgut Reis (Sokak)"},{"id":504976,"il_id":33,"ilce_id":1892,"mahalle_id":182475,"ad":"Turşuoluğu","tip":"Turşuoluğu (Küme Evler)"},{"id":357318,"il_id":33,"ilce_id":1892,"mahalle_id":31912,"ad":"Ucarı","tip":"Ucarı (Sokak)"},{"id":710253570,"il_id":33,"ilce_id":1892,"mahalle_id":31912,"ad":"Ucarı/1","tip":"Ucarı/1 (Sokak)"},{"id":746559,"il_id":33,"ilce_id":1892,"mahalle_id":31911,"ad":"Ulubatlı Hasan","tip":"Ulubatlı Hasan (Sokak)"},{"id":511441,"il_id":33,"ilce_id":1892,"mahalle_id":182463,"ad":"Ulumeres","tip":"Ulumeres (Küme Evler)"},{"id":746560,"il_id":33,"ilce_id":1892,"mahalle_id":31911,"ad":"Uygurlar","tip":"Uygurlar (Sokak)"},{"id":357606,"il_id":33,"ilce_id":1892,"mahalle_id":31910,"ad":"Uzun","tip":"Uzun (Sokak)"},{"id":488663390,"il_id":33,"ilce_id":1892,"mahalle_id":31910,"ad":"Uzun/1","tip":"Uzun/1 (Sokak)"},{"id":358075,"il_id":33,"ilce_id":1892,"mahalle_id":182459,"ad":"Uçarı","tip":"Uçarı (Küme Evler)"},{"id":357262,"il_id":33,"ilce_id":1892,"mahalle_id":31911,"ad":"Vakıf","tip":"Vakıf (Sokak)"},{"id":107305130,"il_id":33,"ilce_id":1892,"mahalle_id":31911,"ad":"Vakıf/1","tip":"Vakıf/1 (Sokak)"},{"id":357607,"il_id":33,"ilce_id":1892,"mahalle_id":31910,"ad":"Vatan","tip":"Vatan (Sokak)"},{"id":357608,"il_id":33,"ilce_id":1892,"mahalle_id":31910,"ad":"Volkan","tip":"Volkan (Sokak)"},{"id":357319,"il_id":33,"ilce_id":1892,"mahalle_id":31912,"ad":"Yaka","tip":"Yaka (Sokak)"},{"id":357263,"il_id":33,"ilce_id":1892,"mahalle_id":31911,"ad":"Yamaç","tip":"Yamaç (Sokak)"},{"id":178520620,"il_id":33,"ilce_id":1892,"mahalle_id":31911,"ad":"Yamaç/1","tip":"Yamaç/1 (Sokak)"},{"id":357264,"il_id":33,"ilce_id":1892,"mahalle_id":31911,"ad":"Yasemen","tip":"Yasemen (Sokak)"},{"id":467310,"il_id":33,"ilce_id":1892,"mahalle_id":31912,"ad":"Yaya","tip":"Yaya (Sokak)"},{"id":357265,"il_id":33,"ilce_id":1892,"mahalle_id":31911,"ad":"Yayla","tip":"Yayla (Sokak)"},{"id":358065,"il_id":33,"ilce_id":1892,"mahalle_id":31912,"ad":"Yağlı","tip":"Yağlı (Sokak)"},{"id":275204,"il_id":33,"ilce_id":1892,"mahalle_id":31911,"ad":"Yaşar Doğu","tip":"Yaşar Doğu (Sokak)"},{"id":358066,"il_id":33,"ilce_id":1892,"mahalle_id":31912,"ad":"Yeni","tip":"Yeni (Sokak)"},{"id":357266,"il_id":33,"ilce_id":1892,"mahalle_id":31911,"ad":"Yetiş","tip":"Yetiş (Sokak)"},{"id":357267,"il_id":33,"ilce_id":1892,"mahalle_id":31911,"ad":"Yeşil","tip":"Yeşil (Sokak)"},{"id":439899,"il_id":33,"ilce_id":1892,"mahalle_id":31911,"ad":"Yeşil Evler","tip":"Yeşil Evler (Sokak)"},{"id":358067,"il_id":33,"ilce_id":1892,"mahalle_id":31912,"ad":"Yoncalı","tip":"Yoncalı (Sokak)"},{"id":472779,"il_id":33,"ilce_id":1892,"mahalle_id":31910,"ad":"Yoğurtcu","tip":"Yoğurtcu (Sokak)"},{"id":357609,"il_id":33,"ilce_id":1892,"mahalle_id":31910,"ad":"Yukarı","tip":"Yukarı (Sokak)"},{"id":302329120,"il_id":33,"ilce_id":1892,"mahalle_id":31910,"ad":"Yukarı/1","tip":"Yukarı/1 (Sokak)"},{"id":622702280,"il_id":33,"ilce_id":1892,"mahalle_id":31910,"ad":"Yukarı/2","tip":"Yukarı/2 (Sokak)"},{"id":357625,"il_id":33,"ilce_id":1892,"mahalle_id":31911,"ad":"Yunus Emre","tip":"Yunus Emre (Sokak)"},{"id":358068,"il_id":33,"ilce_id":1892,"mahalle_id":31912,"ad":"Yurt","tip":"Yurt (Sokak)"},{"id":889125,"il_id":33,"ilce_id":1892,"mahalle_id":31911,"ad":"Yusuf Öncalır","tip":"Yusuf Öncalır (Sokak)"},{"id":357268,"il_id":33,"ilce_id":1892,"mahalle_id":31911,"ad":"Yüksek","tip":"Yüksek (Sokak)"},{"id":890915,"il_id":33,"ilce_id":1892,"mahalle_id":31911,"ad":"Yıldırım","tip":"Yıldırım (Sokak)"},{"id":439897,"il_id":33,"ilce_id":1892,"mahalle_id":31911,"ad":"Yıldırım Beyazıt","tip":"Yıldırım Beyazıt (Sokak)"},{"id":467311,"il_id":33,"ilce_id":1892,"mahalle_id":31912,"ad":"Yıldız","tip":"Yıldız (Sokak)"},{"id":472760,"il_id":33,"ilce_id":1892,"mahalle_id":31910,"ad":"Yılmaz","tip":"Yılmaz (Sokak)"},{"id":423135440,"il_id":33,"ilce_id":1892,"mahalle_id":31910,"ad":"Yılmaz/1","tip":"Yılmaz/1 (Sokak)"},{"id":472780,"il_id":33,"ilce_id":1892,"mahalle_id":31910,"ad":"Zafer","tip":"Zafer (Sokak)"},{"id":357611,"il_id":33,"ilce_id":1892,"mahalle_id":31910,"ad":"Zevzek","tip":"Zevzek (Sokak)"},{"id":357578,"il_id":33,"ilce_id":1892,"mahalle_id":31910,"ad":"Zümrüt","tip":"Zümrüt (Sokak)"},{"id":358069,"il_id":33,"ilce_id":1892,"mahalle_id":31912,"ad":"Çadırgediği","tip":"Çadırgediği (Sokak)"},{"id":275195,"il_id":33,"ilce_id":1892,"mahalle_id":31911,"ad":"Çakıcı","tip":"Çakıcı (Sokak)"},{"id":170573400,"il_id":33,"ilce_id":1892,"mahalle_id":31911,"ad":"Çakıcı/1","tip":"Çakıcı/1 (Sokak)"},{"id":357548,"il_id":33,"ilce_id":1892,"mahalle_id":31910,"ad":"Çakır","tip":"Çakır (Sokak)"},{"id":357579,"il_id":33,"ilce_id":1892,"mahalle_id":31910,"ad":"Çalılı","tip":"Çalılı (Sokak)"},{"id":357271,"il_id":33,"ilce_id":1892,"mahalle_id":31911,"ad":"Çamlı","tip":"Çamlı (Sokak)"},{"id":679386210,"il_id":33,"ilce_id":1892,"mahalle_id":31911,"ad":"Çamlı/1","tip":"Çamlı/1 (Sokak)"},{"id":718836720,"il_id":33,"ilce_id":1892,"mahalle_id":31911,"ad":"Çamlı/2","tip":"Çamlı/2 (Sokak)"},{"id":472767,"il_id":33,"ilce_id":1892,"mahalle_id":31910,"ad":"Çamlıbel","tip":"Çamlıbel (Sokak)"},{"id":357272,"il_id":33,"ilce_id":1892,"mahalle_id":31911,"ad":"Çataklı","tip":"Çataklı (Sokak)"},{"id":357580,"il_id":33,"ilce_id":1892,"mahalle_id":31910,"ad":"Çatal","tip":"Çatal (Sokak)"},{"id":669907890,"il_id":33,"ilce_id":1892,"mahalle_id":31910,"ad":"Çatal/1","tip":"Çatal/1 (Sokak)"},{"id":814293910,"il_id":33,"ilce_id":1892,"mahalle_id":31910,"ad":"Çatal/2","tip":"Çatal/2 (Sokak)"},{"id":357581,"il_id":33,"ilce_id":1892,"mahalle_id":31910,"ad":"Çataloluk","tip":"Çataloluk (Sokak)"},{"id":632207190,"il_id":33,"ilce_id":1892,"mahalle_id":31910,"ad":"Çataloluk/1","tip":"Çataloluk/1 (Sokak)"},{"id":472782,"il_id":33,"ilce_id":1892,"mahalle_id":31911,"ad":"Çatalçam","tip":"Çatalçam (Sokak)"},{"id":995734,"il_id":33,"ilce_id":1892,"mahalle_id":31912,"ad":"Çavuşoğlu","tip":"Çavuşoğlu (Sokak)"},{"id":467312,"il_id":33,"ilce_id":1892,"mahalle_id":31912,"ad":"Çayır","tip":"Çayır (Sokak)"},{"id":357616,"il_id":33,"ilce_id":1892,"mahalle_id":31911,"ad":"Çayır Ekinliği","tip":"Çayır Ekinliği (Cadde)"},{"id":305343090,"il_id":33,"ilce_id":1892,"mahalle_id":31911,"ad":"Çayır Ekinliği/1","tip":"Çayır Ekinliği/1 (Sokak)"},{"id":358070,"il_id":33,"ilce_id":1892,"mahalle_id":31912,"ad":"Çerçi","tip":"Çerçi (Sokak)"},{"id":357617,"il_id":33,"ilce_id":1892,"mahalle_id":31911,"ad":"Çetin","tip":"Çetin (Sokak)"},{"id":664743960,"il_id":33,"ilce_id":1892,"mahalle_id":31911,"ad":"Çetin/1","tip":"Çetin/1 (Sokak)"},{"id":680984,"il_id":33,"ilce_id":1892,"mahalle_id":182459,"ad":"Çeşme","tip":"Çeşme (Küme Evler)"},{"id":358071,"il_id":33,"ilce_id":1892,"mahalle_id":31912,"ad":"Çeşme_1","tip":"Çeşme_1 (Sokak)"},{"id":472783,"il_id":33,"ilce_id":1892,"mahalle_id":31911,"ad":"Çiçekli","tip":"Çiçekli (Sokak)"},{"id":227264910,"il_id":33,"ilce_id":1892,"mahalle_id":31911,"ad":"Çiçekli/1","tip":"Çiçekli/1 (Sokak)"},{"id":357619,"il_id":33,"ilce_id":1892,"mahalle_id":31911,"ad":"Çiğdem","tip":"Çiğdem (Sokak)"},{"id":557218800,"il_id":33,"ilce_id":1892,"mahalle_id":31911,"ad":"Çiğdem/1","tip":"Çiğdem/1 (Sokak)"},{"id":496447,"il_id":33,"ilce_id":1892,"mahalle_id":182475,"ad":"Çiğrin","tip":"Çiğrin (Küme Evler)"},{"id":357618,"il_id":33,"ilce_id":1892,"mahalle_id":31911,"ad":"Çukur","tip":"Çukur (Sokak)"},{"id":357582,"il_id":33,"ilce_id":1892,"mahalle_id":31910,"ad":"Çuvalgı","tip":"Çuvalgı (Sokak)"},{"id":364230100,"il_id":33,"ilce_id":1892,"mahalle_id":31910,"ad":"Çuvalgı /5","tip":"Çuvalgı /5 (Sokak)"},{"id":822581120,"il_id":33,"ilce_id":1892,"mahalle_id":31910,"ad":"Çuvalgı/1","tip":"Çuvalgı/1 (Sokak)"},{"id":340994080,"il_id":33,"ilce_id":1892,"mahalle_id":31910,"ad":"Çuvalgı/2","tip":"Çuvalgı/2 (Sokak)"},{"id":283498190,"il_id":33,"ilce_id":1892,"mahalle_id":31910,"ad":"Çuvalgı/3","tip":"Çuvalgı/3 (Sokak)"},{"id":241935420,"il_id":33,"ilce_id":1892,"mahalle_id":31910,"ad":"Çuvalgı/4","tip":"Çuvalgı/4 (Sokak)"},{"id":467313,"il_id":33,"ilce_id":1892,"mahalle_id":31912,"ad":"Çıtak","tip":"Çıtak (Sokak)"},{"id":357620,"il_id":33,"ilce_id":1892,"mahalle_id":31911,"ad":"Ömeroluğu","tip":"Ömeroluğu (Sokak)"},{"id":149073150,"il_id":33,"ilce_id":1892,"mahalle_id":31912,"ad":"Ömeroluğu","tip":"Ömeroluğu (Sokak)"},{"id":144369920,"il_id":33,"ilce_id":1892,"mahalle_id":31911,"ad":"Ömeroluğu/1","tip":"Ömeroluğu/1 (Sokak)"},{"id":457718050,"il_id":33,"ilce_id":1892,"mahalle_id":31912,"ad":"Ömeroluğu/1","tip":"Ömeroluğu/1 (Sokak)"},{"id":472768,"il_id":33,"ilce_id":1892,"mahalle_id":31910,"ad":"Üst","tip":"Üst (Sokak)"},{"id":358072,"il_id":33,"ilce_id":1892,"mahalle_id":31912,"ad":"Ütük","tip":"Ütük (Sokak)"},{"id":472784,"il_id":33,"ilce_id":1892,"mahalle_id":31911,"ad":"Üzümlü","tip":"Üzümlü (Sokak)"},{"id":504480,"il_id":33,"ilce_id":1892,"mahalle_id":182467,"ad":"ş. J. Yzb. Halil Özdemir","tip":"ş. J. Yzb. Halil Özdemir (Küme Evler)"},{"id":504644,"il_id":33,"ilce_id":1892,"mahalle_id":182467,"ad":"ş. J. Yzb. Halil Özdemir 2","tip":"ş. J. Yzb. Halil Özdemir 2 (Küme Evler)"},{"id":357621,"il_id":33,"ilce_id":1892,"mahalle_id":31911,"ad":"şAhin","tip":"şAhin (Sokak)"},{"id":357622,"il_id":33,"ilce_id":1892,"mahalle_id":31911,"ad":"şAmlar","tip":"şAmlar (Sokak)"},{"id":357544,"il_id":33,"ilce_id":1892,"mahalle_id":31910,"ad":"şArlak","tip":"şArlak (Sokak)"},{"id":358073,"il_id":33,"ilce_id":1892,"mahalle_id":31912,"ad":"şArşar","tip":"şArşar (Sokak)"},{"id":890922,"il_id":33,"ilce_id":1892,"mahalle_id":31911,"ad":"şEhit Er Mustafa Oğuz","tip":"şEhit Er Mustafa Oğuz (Sokak)"},{"id":357610,"il_id":33,"ilce_id":1892,"mahalle_id":31910,"ad":"şEhit j.kom.çvş. Aziz Akkoca","tip":"şEhit j.kom.çvş. Aziz Akkoca (Sokak)"},{"id":776133700,"il_id":33,"ilce_id":1892,"mahalle_id":31912,"ad":"şEhit j.kom.çvş. Aziz Akkoca","tip":"şEhit j.kom.çvş. Aziz Akkoca (Sokak)"},{"id":702659,"il_id":33,"ilce_id":1892,"mahalle_id":31912,"ad":"şEhit Üsteğmen Ismet Akın","tip":"şEhit Üsteğmen Ismet Akın (Sokak)"},{"id":357623,"il_id":33,"ilce_id":1892,"mahalle_id":31911,"ad":"şEker","tip":"şEker (Sokak)"},{"id":472785,"il_id":33,"ilce_id":1892,"mahalle_id":31911,"ad":"şEn","tip":"şEn (Sokak)"},{"id":912186360,"il_id":33,"ilce_id":1892,"mahalle_id":31911,"ad":"şEn/1","tip":"şEn/1 (Sokak)"},{"id":357545,"il_id":33,"ilce_id":1892,"mahalle_id":31910,"ad":"şIrin","tip":"şIrin (Sokak)"}]